Workbook
Name SegmentaciónDeDatos_CANT_UND2: #REF!
Name SegmentaciónDeDatos_Categoría: #REF!
Name SegmentaciónDeDatos_COMPRA: #REF!
Name SegmentaciónDeDatos_NEGOCIO: #REF!
Name SlicerCache_Table_1_Col_1: #N/A
Name SlicerCache_Table_1_Col_16: #N/A
Name SlicerCache_Table_1_Col_2: #N/A
Name SlicerCache_Table_1_Col_7: #N/A

Sheet CAT FOCO SEM1 SEP
C1: CERVEZA
C2: PCV
D5: =12+17+3+17 -> 49
F7: %Cer | G7: %Mal | H7: %Sang | I7: %Vinos | J7: % Cola Negra | K7: % Cola Blanca | L7: %Sab | M7: %Agua | N7: %Jug | O7: %Té | P7: %Beb.Depor. | Q7: %Mezcladores | R7: %Harina de Maíz | S7: %Margarinas | T7: %Mayonesas | U7: %Quesos | V7: %Achocolatados | W7: %Pepitonas | X7: %Atunes | Y7: %Cereales Infantiles | Z7: %Manteca | AA7: %Oleinas | AB7: %Ket | AC7: %Aceites | AD7: %Vin | AE7: %Arroz | AF7: %Past | AG7: %Avena | AH7: %Cafe | AI7: %Yogurt | AJ7: %Perros | AK7: %Gatos | AL7: %Sar | AM7: %Deter | AN7: %Multiuso | AO7: %Suavizantes de Ropa | AP7: %Limpiadores | AQ7: %Lavaplatos | AR7: %Jab | AS7: %Cuidado del Cabello | AT7: %Cuidado Femenino | AU7: %Cuidado Personal | AV7: %Cuidado del Bebé | AW7: %Cuidado Bucal | AX7: %Afeitado | AY7: ROCKSTAR | AZ7: MIN SPRK TOR P500 12U | BA7: MALTIN COCO
A8: CODIGO SISTEMA | B8: CEP | C8: DIA | D8: CLIENTE | E8: CLIENTES DE ADC
A9: 0190330032 | B9: 939228 | C9: LUNES | D9: DIAZ INVERSIONES LA ANDINA
A10: 0084357812 | B10: 84695 | C10: LUNES | D10: INVERSIONES ECONOMICASA
A11: 412818023 | B11: 945177 | C11: LUNES | D11: FARMACIA DEL AHORRO PEDRAZA, C.A | E11: 1 PUERTA
A12: 0084412364 | B12: 278935 | C12: LUNES | D12: YONGCUN WU / WU COMERCIAL LUNA 2014, F.P
A13: 175493685 | B13: 961367 | C13: LUNES | D13: BODEGON EL CALDEREÑO
A14: 128256373 | B14: 874150 | C14: LUNES | D14: CLUB DEPORTIVO EL JARDIN FP | E14: 1 PUERTA
A15: 0080090184 | B15: 632997 | C15: LUNES | D15: TORRES POSADA TURISTICA SANTOCRISTO A-Z
A16: V196206953 | B16: 936151 | C16: LUNES | D16: BELANDRIA PANADERIA CENTRAL ELIPAN F,P
A17: V099858687 | B17: 8408792 | C17: LUNES | D17: OMAIRA DEL CARMEN OCANTO
A18: 230228139 | B18: 8408877 | C18: MARTES | D18: JOSE ADRIAN VIRIGAY
A19: V169783388 | B19: 623584 | C19: MARTES | D19: MORENO INVERSIONES DON PALILLO F.P | E19: 1 PUERTA
A20: 0413051907 | B20: 959624 | C20: MARTES | D20: INVERSIONES ALJARAMANI | E20: 1 PUERTA
A21: 0153309953 | B21: 945055 | C21: MARTES | D21: PIDIACHI INVERSIONES MI TESORO, F.P
A22: 050326175 | B22: 549351 | C22: MARTES | D22: LICORES YENDER | E22: 1 PUERTA
A23: 103997077 | B23: 145691 | C23: MARTES | D23: REST. CERV. EL GRAN MESON | E23: 1 PUERTA
A24: 004881148 | B24: 78643 | C24: MARTES | D24: BAR REST PARIAGUAN | E24: 1 PUERTA
A25: 0009363745 | B25: 549506 | C25: MARTES | D25: LICORERIA LOS LAURELES | E25: 1 PUERTA
A26: 165750817 | B26: 960511 | C26: MARTES | D26: KARELIS YARUBI VILLARREAL CASTILLO
A27: 091811606 | B27: 623587 | C27: MARTES | D27: BODEGON EL AMANECER
A28: 0017550000 | B28: 701396 | C28: MARTES | D28: YASMIN DEL CARMEN PERNIA PEREZ | E28: 1 PUERTA
A29: 148679971 | B29: 943440 | C29: MARTES | D29: MORALES INV. EL LLANO, F.P | E29: 1 PUERTA
A30: 0230220332 | B30: 566611 | C30: MARTES | D30: SUAREZ RESTOBAR Y BODEGON DESTAPALA, F.P | E30: 1 PUERTA
A31: 093655857 | B31: 569007 | C31: MARTES | D31: CASTILLO BODEGON DON JOSE, F.P
A32: 0502689125 | B32: 949130 | C32: MARTES | D32: MULTI-INVERSIONES EL TAMARINDO, C.A | E32: 1 PUERTA
A33: 0065937405 | B33: 145712 | C33: MARTES | D33: VIVERES Y FRUTERIA EL CHAPARRAL
A34: 0408654261 | B34: 420131 | C34: MARTES | D34: ABASTO Y LICORERIA LA CHINA, C.A
A35: 192441214 | B35: 623573 | C35: MARTES | D35: BODEGON INVERSIONES VAMOS PA´ YI | E35: 1 PUERTA
A36: 0410773120 | B36: 936187 | C36: MARTES | D36: AVENDAÑO BODEGON EUKARY-G.E FP | E36: 1 PUERTA
A37: 036177027 | B37: 145626 | C37: MARTES | D37: CERVECERIA LA COPA DE ORO | E37: 1 PUERTA
A38: J411565342 | B38: 566628 | C38: MARTES | D38: LICORERIA EL MARACUCHO
A39: 0283771810 | B39: 8408938 | C39: MARTES | D39: GREGORIO ISAA MILLAN AGUIRRE
A40: 0081364881 | B40: 333777 | C40: MARTES | D40: LICORES EL VIÑEDO, F.P.
A41: CLTAINA-000050 | B41: 961522 | C41: MIERCOLES | D41: BELANDRIA SERVICARNES LOS COMPADRES, F.P.
B42: 145689 | C42: MIERCOLES | D42: VIVERES DONEY
A43: 0406629260 | B43: 893765 | C43: MIERCOLES | D43: CD MASTER, C.A
A44: 0049560385 | B44: 349963 | C44: MIERCOLES | D44: FERNANDEZ CARLOS ALFONSO
A45: 0030666499 | B45: 945108 | C45: MIERCOLES | D45: LADINO PANADERIA LA SOLIDARIA
A46: 0048510961 | B46: 141682 | C46: MIERCOLES | D46: MARTINEZ VIVERES FRUTERIA QUINCALL ERIA Y FERRETERIA DON NELSON, F.P
A47: 0198265167 | B47: 939226 | C47: MIERCOLES | D47: JESÚS EDUARDO PÉREZ PÉREZ
A48: 0500767510 | B48: 913779 | C48: MIERCOLES | D48: MULTI-INVERSIONES IZANAGI, C.A | E48: 3 PUERTA
A49: 505484818 | B49: 942919 | C49: MIERCOLES | D49: FARMACIA SAN GREGORIO PEDRAZA
A50: 0015462346 | B50: 111570 | C50: MIERCOLES | D50: JUAN CARLOS GUERRERO CORDERO | E50: 2 PUERTA
A51: 0040561300 | B51: 395465 | C51: MIERCOLES | D51: LLANO MARKET EXPRESS, C.A | E51: 1 PUERTA
A52: 0139474127 | B52: 949154 | C52: MIERCOLES | D52: CELIX CHARLI AVILA RANGEL
A53: 0275645326 | B53: 949163 | C53: MIERCOLES | D53: LISETH ANDREINA YEGUES BRICEÑO
A54: 0180460531 | B54: 84833 | C54: MIERCOLES | D54: INVERSIONES LA CAMPIÑA EXPRESS2309
A55: 0012205241 | B55: 910716 | C55: MIERCOLES | D55: CHINCHILLA INVERSIONES 965 AMS, F.P.
A56: 0025077807 | B56: 939205 | C56: MIERCOLES | D56: COLMENARES INVERSIONES DEMS FP
A57: 0021538418 | B57: 945186 | C57: MIERCOLES | D57: LUZ DARY CIFUENTES DE CONTRERAS
A58: 19518635 | B58: 8413243 | C58: MIERCOLES | D58: OSMARY LILIBETH AGUILAR
A59: V093634663 | B59: 8404790 | C59: MIERCOLES | D59: DUARTE LICORERIA MI POTRILLO, F.P
A60: 0092601206 | B60: 145696 | C60: JUEVES | D60: DISTRIBUIDORA MARWIL 2002
A61: 0501043060 | B61: 945056 | C61: JUEVES | D61: FARMACIA LA ESPERANZA, C.A
A62: 0410747714 | B62: 623599 | C62: JUEVES | D62: SALCEDO INVERSIONES EL COLOMBIANO
A63: 188380898 | B63: 924406 | C63: JUEVES | D63: INVERSIONES DISTRIBUIDORA & BODEGÓN DOÑA PAULA, C.A
... A67: 0179871811 | B67: 84941 | C67: JUEVES | D67: CARNICERIA Y CHARCUTERIA INVERSIONES LA PEDRACEÑA XXI, F.P
B68: 851970 | C68: JUEVES | D68: INV JANIFOX SYSTEMS
A69: 0141317985 | B69: 936180 | C69: JUEVES | D69: DURAN INVERSIONES MI PEQUEÑA GOTITA
A70: 0192434382 | B70: 939288 | C70: JUEVES | D70: CASTILLO INVERSIONES ONE CHOS, F.P | E70: 1 PUERTA
A71: 0411973580 | B71: 960505 | C71: JUEVES | D71: PANADERIA Y PASTELERIA EL CRISTAL, C.A | E71: 2 PUERTA
A72: 0023039790 | B72: 945052 | C72: JUEVES | D72: ROMERO INVERSIONES JONATHAN
A73: 0015968631 | B73: 576649 | C73: JUEVES | D73: LUNCH LA SASON DE MAMA
A74: 0412149318 | B74: 936149 | C74: JUEVES | D74: INVERSIONES Y HELADERIA RIVAS J.R.,
A75: V166359682 | B75: 8404818 | C75: JUEVES | D75: HECTOR DANIEL MACIAS (LA GRAN PARADA)
A76: 0017527450 | B76: 939349 | C76: VIERNES | D76: AGUIRRE FERREINVERSIONES TODO PARA USTED, F.P
A77: 0500466609 | B77: 924432 | C77: VIERNES | D77: BODEGON CITY MARKET, C.A.
A78: 0130381584 | B78: 627484 | C78: VIERNES | D78: PANADERIA Y PASTELERIA PLAZA PAEZ | E78: 2 PUERTA
A79: 0262297310 | B79: 841172 | C79: VIERNES | D79: PANADERIA Y CHARCUTERIA EL TACHIREN CE L.F | E79: 2 PUERTA
A80: 0296237484 | B80: 924339 | C80: VIERNES | D80: FENG INVERSIONES EL 888 | E80: 2 PUERTA
A81: 0204069014 | B81: 852800 | C81: VIERNES | D81: SUPERMERCADO ECONOMICO 2012 | E81: 1 PUERTA
A82: 0014059537 | B82: 910784 | C82: VIERNES | D82: PEREZ INVERSIONES OCTARYKELY, F.P | E82: 2 PUERTA
A83: 0500254504 | B83: 913684 | C83: VIERNES | D83: MERCATODO Q BUENO, C.A | E83: 1 PUERTA
A84: 0213198536 | B84: 913732 | C84: VIERNES | D84: ROMERO INVERSIONES EL REGALO, FP
A85: 0410700076 | B85: 913734 | C85: VIERNES | D85: EL TUKUTICO DE PAPÁ, C.A.
A86: 0083116447 | B86: 913771 | C86: VIERNES | D86: ZHEN DISTRIBUIDORA NEOMODA, F.P
A87: 0285714482 | B87: 943464 | C87: VIERNES | D87: MORA BODEGON EL DESCUENTO, F.P
A88: 310161542 | B88: 66963 | C88: VIERNES | D88: BAR REST. EL MONJE | E88: 1 PUERTA
A89: 0406633623 | B89: 305849 | C89: VIERNES | D89: MULTI-INVERSIONES SANCHEZMOLINA | E89: 1 PUERTA
A90: 0412577107 | B90: 913690 | C90: VIERNES | D90: INVERSIONES CACHILAPO C.A
A91: 0013229371 | B91: 913699 | C91: VIERNES | D91: PEREZ PANADERIA Y PASTELERIA YVANIS F.P.
A92: V254680814 | B92: 8405078 | C92: VIERNES | D92: JIMENEZ PANADERIA LA CITA DIVINA

Sheet INVENTARIO
A10: NEGOCIO | B10: Categoría | C10: Marca | D10: COD | E10: DESC | F10: UND | G10: COMPRA | H10: UND2 | I10: SEM1 | J10: SEM2 | K10: VENTA | L10: SEM3 | M10: VENTA2 | N10: SEM4 | O10: SEM5 | P10: CANT UND2 | Q10: COMP | R10: VENTA | S10: VENTA2,1 | T10: VENTAS 3
A11: =VLOOKUP(INVENTARIO!$D11,LISTA!$A:$E,3,0) -> APC-FQ | B11: =VLOOKUP(INVENTARIO!$D11,LISTA!$A:$E,4,0) -> Yogurt | C11: =VLOOKUP(INVENTARIO!$D11,LISTA!$A:$E,5,0) -> MIGURT | D11: Y070 | E11: YOGURT SABOR NARANJA V-MIGURT 125GX24UND | F11: 24 | G11: =Q11 -> 0 | H11: =G11*F11 -> 0 | K11: =R11 -> 0 | M11: =S11 -> 0 | P11: =H11-J11-I11-K11-L11-M11-INVENTARIO!$N11-O11 -> 0 | Q11: =IFERROR(VLOOKUP(D11,'TABL COMPR'!$A:$D,4,0),0) -> 0 | R11: =IFERROR(VLOOKUP(D11,#REF!,4,0),0) -> 0 | S11: =IFERROR(VLOOKUP(D11,#REF!,4,0),0) -> 0 | T11: =IFERROR(VLOOKUP(D11,#REF!,4,0),0) -> 0
A12: =VLOOKUP(INVENTARIO!$D12,LISTA!$A:$E,3,0) -> APC-FQ | B12: =VLOOKUP(INVENTARIO!$D12,LISTA!$A:$E,4,0) -> Yogurt | C12: =VLOOKUP(INVENTARIO!$D12,LISTA!$A:$E,5,0) -> MIGURT | D12: Y069 | E12: YOGURT SABOR CAMBUR MIGURT 125GX24UND | F12: 24 | G12: =Q12 -> 0 | H12: =G12*F12 -> 0 | K12: =R12 -> 0 | M12: =S12 -> 0 | P12: =H12-J12-I12-K12-L12-M12-INVENTARIO!$N12-O12 -> 0 | Q12: =IFERROR(VLOOKUP(D12,'TABL COMPR'!$A:$D,4,0),0) -> 0 | R12: =IFERROR(VLOOKUP(D12,#REF!,4,0),0) -> 0 | S12: =IFERROR(VLOOKUP(D12,#REF!,4,0),0) -> 0 | T12: =IFERROR(VLOOKUP(D12,#REF!,4,0),0) -> 0
A13: =VLOOKUP(INVENTARIO!$D13,LISTA!$A:$E,3,0) -> APC-FQ | B13: =VLOOKUP(INVENTARIO!$D13,LISTA!$A:$E,4,0) -> Yogurt | C13: =VLOOKUP(INVENTARIO!$D13,LISTA!$A:$E,5,0) -> MIGURT | D13: Y036 | E13: YOGURT SABOR FRESA MIGURT 125GX24UND | F13: 24 | G13: =Q13 -> 0 | H13: =G13*F13 -> 0 | K13: =R13 -> 0 | M13: =S13 -> 0 | P13: =H13-J13-I13-K13-L13-M13-INVENTARIO!$N13-O13 -> 0 | Q13: =IFERROR(VLOOKUP(D13,'TABL COMPR'!$A:$D,4,0),0) -> 0 | R13: =IFERROR(VLOOKUP(D13,#REF!,4,0),0) -> 0 | S13: =IFERROR(VLOOKUP(D13,#REF!,4,0),0) -> 0 | T13: =IFERROR(VLOOKUP(D13,#REF!,4,0),0) -> 0
A14: =VLOOKUP(INVENTARIO!$D14,LISTA!$A:$E,3,0) -> APC-FQ | B14: =VLOOKUP(INVENTARIO!$D14,LISTA!$A:$E,4,0) -> Yogurt | C14: =VLOOKUP(INVENTARIO!$D14,LISTA!$A:$E,5,0) -> MIGURT | D14: Y007 | E14: YOGURT FRUTA FRESA MIGURT 750GX12UND BOT | F14: 12 | G14: =Q14 -> 0 | H14: =G14*F14 -> 0 | K14: =R14 -> 0 | M14: =S14 -> 0 | P14: =H14-J14-I14-K14-L14-M14-INVENTARIO!$N14-O14 -> 0 | Q14: =IFERROR(VLOOKUP(D14,'TABL COMPR'!$A:$D,4,0),0) -> 0 | R14: =IFERROR(VLOOKUP(D14,#REF!,4,0),0) -> 0 | S14: =IFERROR(VLOOKUP(D14,#REF!,4,0),0) -> 0 | T14: =IFERROR(VLOOKUP(D14,#REF!,4,0),0) -> 0
A15: =VLOOKUP(INVENTARIO!$D15,LISTA!$A:$E,3,0) -> APC-FQ | B15: =VLOOKUP(INVENTARIO!$D15,LISTA!$A:$E,4,0) -> Yogurt | C15: =VLOOKUP(INVENTARIO!$D15,LISTA!$A:$E,5,0) -> MIGURT | D15: Y005 | E15: YOGURT FRUTA DURAZNO MIGURT 250GX24UND | F15: 24 | G15: =Q15 -> 0 | H15: =G15*F15 -> 0 | K15: =R15 -> 0 | M15: =S15 -> 0 | P15: =H15-J15-I15-K15-L15-M15-INVENTARIO!$N15-O15 -> 0 | Q15: =IFERROR(VLOOKUP(D15,'TABL COMPR'!$A:$D,4,0),0) -> 0 | R15: =IFERROR(VLOOKUP(D15,#REF!,4,0),0) -> 0 | S15: =IFERROR(VLOOKUP(D15,#REF!,4,0),0) -> 0 | T15: =IFERROR(VLOOKUP(D15,#REF!,4,0),0) -> 0
A16: =VLOOKUP(INVENTARIO!$D16,LISTA!$A:$E,3,0) -> APC-FQ | B16: =VLOOKUP(INVENTARIO!$D16,LISTA!$A:$E,4,0) -> Yogurt | C16: =VLOOKUP(INVENTARIO!$D16,LISTA!$A:$E,5,0) -> MIGURT | D16: Y004 | E16: YOGURT FRUTA FRESA MIGURT 250GX24UND | F16: 24 | G16: =Q16 -> 0 | H16: =G16*F16 -> 0 | K16: =R16 -> 0 | M16: =S16 -> 0 | P16: =H16-J16-I16-K16-L16-M16-INVENTARIO!$N16-O16 -> 0 | Q16: =IFERROR(VLOOKUP(D16,'TABL COMPR'!$A:$D,4,0),0) -> 0 | R16: =IFERROR(VLOOKUP(D16,#REF!,4,0),0) -> 0 | S16: =IFERROR(VLOOKUP(D16,#REF!,4,0),0) -> 0 | T16: =IFERROR(VLOOKUP(D16,#REF!,4,0),0) -> 0
A17: =VLOOKUP(INVENTARIO!$D17,LISTA!$A:$E,3,0) -> APC-FQ | B17: =VLOOKUP(INVENTARIO!$D17,LISTA!$A:$E,4,0) -> Yogurt | C17: =VLOOKUP(INVENTARIO!$D17,LISTA!$A:$E,5,0) -> MIGURT | D17: Y002 | E17: YOGURT FRUTA DURAZNO MIGURT 125GX24UND | F17: 24 | G17: =Q17 -> 0 | H17: =G17*F17 -> 0 | K17: =R17 -> 0 | M17: =S17 -> 0 | P17: =H17-J17-I17-K17-L17-M17-INVENTARIO!$N17-O17 -> 0 | Q17: =IFERROR(VLOOKUP(D17,'TABL COMPR'!$A:$D,4,0),0) -> 0 | R17: =IFERROR(VLOOKUP(D17,#REF!,4,0),0) -> 0 | S17: =IFERROR(VLOOKUP(D17,#REF!,4,0),0) -> 0 | T17: =IFERROR(VLOOKUP(D17,#REF!,4,0),0) -> 0
A18: =VLOOKUP(INVENTARIO!$D18,LISTA!$A:$E,3,0) -> APC-FQ | B18: =VLOOKUP(INVENTARIO!$D18,LISTA!$A:$E,4,0) -> Yogurt | C18: =VLOOKUP(INVENTARIO!$D18,LISTA!$A:$E,5,0) -> MIGURT | D18: Y001 | E18: YOGURT FRUTA FRESA MIGURT 125GX24UND | F18: 24 | G18: =Q18 -> 0 | H18: =G18*F18 -> 0 | K18: =R18 -> 0 | M18: =S18 -> 0 | P18: =H18-J18-I18-K18-L18-M18-INVENTARIO!$N18-O18 -> 0 | Q18: =IFERROR(VLOOKUP(D18,'TABL COMPR'!$A:$D,4,0),0) -> 0 | R18: =IFERROR(VLOOKUP(D18,#REF!,4,0),0) -> 0 | S18: =IFERROR(VLOOKUP(D18,#REF!,4,0),0) -> 0 | T18: =IFERROR(VLOOKUP(D18,#REF!,4,0),0) -> 0
A19: =VLOOKUP(INVENTARIO!$D19,LISTA!$A:$E,3,0) -> APC-FQ | B19: =VLOOKUP(INVENTARIO!$D19,LISTA!$A:$E,4,0) -> HARINA DE MAIZ | C19: =VLOOKUP(INVENTARIO!$D19,LISTA!$A:$E,5,0) -> PAN | D19: H187 | E19: PAN HPM BLANCO GLUTEN FREE 1KGX20UN VE | F19: 20 | G19: =Q19 -> 0 | H19: =G19*F19 -> 0 | K19: =R19 -> 0 | M19: =S19 -> 0 | P19: =H19-J19-I19-K19-L19-M19-INVENTARIO!$N19-O19 -> 0 | Q19: =IFERROR(VLOOKUP(D19,'TABL COMPR'!$A:$D,4,0),0) -> 0 | R19: =IFERROR(VLOOKUP(D19,#REF!,4,0),0) -> 0 | S19: =IFERROR(VLOOKUP(D19,#REF!,4,0),0) -> 0 | T19: =IFERROR(VLOOKUP(D19,#REF!,4,0),0) -> 0
A20: =VLOOKUP(INVENTARIO!$D20,LISTA!$A:$E,3,0) -> APC-FQ | B20: =VLOOKUP(INVENTARIO!$D20,LISTA!$A:$E,4,0) -> MAYONESAS | C20: =VLOOKUP(INVENTARIO!$D20,LISTA!$A:$E,5,0) -> MAVESA | D20: T020 | E20: MAVESA MAYONESA 445Gx12UN | F20: 12 | G20: =Q20 -> 0 | H20: =G20*F20 -> 0 | K20: =R20 -> 0 | M20: =S20 -> 0 | P20: =H20-J20-I20-K20-L20-M20-INVENTARIO!$N20-O20 -> 0 | Q20: =IFERROR(VLOOKUP(D20,'TABL COMPR'!$A:$D,4,0),0) -> 0 | R20: =IFERROR(VLOOKUP(D20,#REF!,4,0),0) -> 0 | S20: =IFERROR(VLOOKUP(D20,#REF!,4,0),0) -> 0 | T20: =IFERROR(VLOOKUP(D20,#REF!,4,0),0) -> 0
A21: =VLOOKUP(INVENTARIO!$D21,LISTA!$A:$E,3,0) -> APC-FQ | B21: =VLOOKUP(INVENTARIO!$D21,LISTA!$A:$E,4,0) -> KETCHUP | C21: =VLOOKUP(INVENTARIO!$D21,LISTA!$A:$E,5,0) -> PAMPERO | D21: T061 | E21: PAMPERO KETCHUP 397Gx24UN | F21: 24 | G21: =Q21 -> 0 | H21: =G21*F21 -> 0 | K21: =R21 -> 0 | M21: =S21 -> 0 | P21: =H21-J21-I21-K21-L21-M21-INVENTARIO!$N21-O21 -> 0 | Q21: =IFERROR(VLOOKUP(D21,'TABL COMPR'!$A:$D,4,0),0) -> 0 | R21: =IFERROR(VLOOKUP(D21,#REF!,4,0),0) -> 0 | S21: =IFERROR(VLOOKUP(D21,#REF!,4,0),0) -> 0 | T21: =IFERROR(VLOOKUP(D21,#REF!,4,0),0) -> 0
A22: =VLOOKUP(INVENTARIO!$D22,LISTA!$A:$E,3,0) -> APC-FQ | B22: =VLOOKUP(INVENTARIO!$D22,LISTA!$A:$E,4,0) -> MARGARINA | C22: =VLOOKUP(INVENTARIO!$D22,LISTA!$A:$E,5,0) -> MAVESA | D22: T595 | E22: MAVESA MARGARINA 250Gx24UN | F22: 24 | G22: =Q22 -> 0 | H22: =G22*F22 -> 0 | K22: =R22 -> 0 | M22: =S22 -> 0 | P22: =H22-J22-I22-K22-L22-M22-INVENTARIO!$N22-O22 -> 0 | Q22: =IFERROR(VLOOKUP(D22,'TABL COMPR'!$A:$D,4,0),0) -> 0 | R22: =IFERROR(VLOOKUP(D22,#REF!,4,0),0) -> 0 | S22: =IFERROR(VLOOKUP(D22,#REF!,4,0),0) -> 0 | T22: =IFERROR(VLOOKUP(D22,#REF!,4,0),0) -> 0
... A36: =VLOOKUP(INVENTARIO!$D36,LISTA!$A:$E,3,0) -> APC-FQ | B36: =VLOOKUP(INVENTARIO!$D36,LISTA!$A:$E,4,0) -> MAYONESAS | C36: =VLOOKUP(INVENTARIO!$D36,LISTA!$A:$E,5,0) -> MAVESA | D36: T018 | E36: MAVESA MAYONESA 910Gx6UN | F36: 6 | G36: =Q36 -> 0 | H36: =G36*F36 -> 0 | K36: =R36 -> 0 | M36: =S36 -> 0 | P36: =H36-J36-I36-K36-L36-M36-INVENTARIO!$N36-O36 -> 0 | Q36: =IFERROR(VLOOKUP(D36,'TABL COMPR'!$A:$D,4,0),0) -> 0 | R36: =IFERROR(VLOOKUP(D36,#REF!,4,0),0) -> 0 | S36: =IFERROR(VLOOKUP(D36,#REF!,4,0),0) -> 0 | T36: =IFERROR(VLOOKUP(D36,#REF!,4,0),0) -> 0
A37: =VLOOKUP(INVENTARIO!$D37,LISTA!$A:$E,3,0) -> APC-FQ | B37: =VLOOKUP(INVENTARIO!$D37,LISTA!$A:$E,4,0) -> MODIFICADORES LACTEOS BEBIDAS | C37: =VLOOKUP(INVENTARIO!$D37,LISTA!$A:$E,5,0) -> TODDY | D37: T003 | E37: TODDY BOLSA 400GX24UN | F37: 24 | G37: 0 | H37: =G37*F37 -> 0 | K37: =R37 -> 0 | M37: =S37 -> 0 | P37: =H37-J37-I37-K37-L37-M37-INVENTARIO!$N37-O37 -> 0 | Q37: =IFERROR(VLOOKUP(D37,'TABL COMPR'!$A:$D,4,0),0) -> 0 | R37: =IFERROR(VLOOKUP(D37,#REF!,4,0),0) -> 0 | S37: =IFERROR(VLOOKUP(D37,#REF!,4,0),0) -> 0 | T37: =IFERROR(VLOOKUP(D37,#REF!,4,0),0) -> 0
A38: =VLOOKUP(INVENTARIO!$D38,LISTA!$A:$E,3,0) -> APC-FQ | B38: =VLOOKUP(INVENTARIO!$D38,LISTA!$A:$E,4,0) -> MODIFICADORES LACTEOS BEBIDAS | C38: =VLOOKUP(INVENTARIO!$D38,LISTA!$A:$E,5,0) -> TODDY | D38: T002 | E38: TODDY 2KGx8UN | F38: 8 | G38: =Q38 -> 0 | H38: =G38*F38 -> 0 | K38: =R38 -> 0 | M38: =S38 -> 0 | P38: =H38-J38-I38-K38-L38-M38-INVENTARIO!$N38-O38 -> 0 | Q38: =IFERROR(VLOOKUP(D38,'TABL COMPR'!$A:$D,4,0),0) -> 0 | R38: =IFERROR(VLOOKUP(D38,#REF!,4,0),0) -> 0 | S38: =IFERROR(VLOOKUP(D38,#REF!,4,0),0) -> 0 | T38: =IFERROR(VLOOKUP(D38,#REF!,4,0),0) -> 0
A39: =VLOOKUP(INVENTARIO!$D39,LISTA!$A:$E,3,0) -> APC-FQ | B39: =VLOOKUP(INVENTARIO!$D39,LISTA!$A:$E,4,0) -> VINAGRES | C39: =VLOOKUP(INVENTARIO!$D39,LISTA!$A:$E,5,0) -> MAVESA | D39: T049 | E39: MAVESA VINAGRE 500MLx24UN | F39: 24 | G39: =Q39 -> 0 | H39: =G39*F39 -> 0 | K39: =R39 -> 0 | M39: =S39 -> 0 | P39: =H39-J39-I39-K39-L39-M39-INVENTARIO!$N39-O39 -> 0 | Q39: =IFERROR(VLOOKUP(D39,'TABL COMPR'!$A:$D,4,0),0) -> 0 | R39: =IFERROR(VLOOKUP(D39,#REF!,4,0),0) -> 0 | S39: =IFERROR(VLOOKUP(D39,#REF!,4,0),0) -> 0 | T39: =IFERROR(VLOOKUP(D39,#REF!,4,0),0) -> 0
A40: =VLOOKUP(INVENTARIO!$D40,LISTA!$A:$E,3,0) -> APC-FQ | B40: =VLOOKUP(INVENTARIO!$D40,LISTA!$A:$E,4,0) -> KETCHUP | C40: =VLOOKUP(INVENTARIO!$D40,LISTA!$A:$E,5,0) -> PAMPERO | D40: T060 | E40: KETCHUP PAMPERO 198 G X 24 UND | F40: 24 | G40: =Q40 -> 0 | H40: =G40*F40 -> 0 | K40: =R40 -> 0 | M40: =S40 -> 0 | P40: =H40-J40-I40-K40-L40-M40-INVENTARIO!$N40-O40 -> 0 | Q40: =IFERROR(VLOOKUP(D40,'TABL COMPR'!$A:$D,4,0),0) -> 0 | R40: =IFERROR(VLOOKUP(D40,#REF!,4,0),0) -> 0 | S40: =IFERROR(VLOOKUP(D40,#REF!,4,0),0) -> 0 | T40: =IFERROR(VLOOKUP(D40,#REF!,4,0),0) -> 0
A41: =VLOOKUP(INVENTARIO!$D41,LISTA!$A:$E,3,0) -> APC-FQ | B41: =VLOOKUP(INVENTARIO!$D41,LISTA!$A:$E,4,0) -> BEBIDAS INSTANTANEAS | C41: =VLOOKUP(INVENTARIO!$D41,LISTA!$A:$E,5,0) -> KONGA | D41: Q142 | E41: KONGA PAPELON CON LIMON 30GX8X14UNI | F41: 14 | G41: =Q41 -> 0 | H41: =G41*F41 -> 0 | K41: =R41 -> 0 | M41: =S41 -> 0 | P41: =H41-J41-I41-K41-L41-M41-INVENTARIO!$N41-O41 -> 0 | Q41: =IFERROR(VLOOKUP(D41,'TABL COMPR'!$A:$D,4,0),0) -> 0 | R41: =IFERROR(VLOOKUP(D41,#REF!,4,0),0) -> 0 | S41: =IFERROR(VLOOKUP(D41,#REF!,4,0),0) -> 0 | T41: =IFERROR(VLOOKUP(D41,#REF!,4,0),0) -> 0
A42: =VLOOKUP(INVENTARIO!$D42,LISTA!$A:$E,3,0) -> APC-FQ | B42: =VLOOKUP(INVENTARIO!$D42,LISTA!$A:$E,4,0) -> BEBIDAS INSTANTANEAS | C42: =VLOOKUP(INVENTARIO!$D42,LISTA!$A:$E,5,0) -> KONGA | D42: Q141 | E42: KONGA SABOR DURAZNO 30GX8X14UN | F42: 14 | G42: =Q42 -> 0 | H42: =G42*F42 -> 0 | K42: =R42 -> 0 | M42: =S42 -> 0 | P42: =H42-J42-I42-K42-L42-M42-INVENTARIO!$N42-O42 -> 0 | Q42: =IFERROR(VLOOKUP(D42,'TABL COMPR'!$A:$D,4,0),0) -> 0 | R42: =IFERROR(VLOOKUP(D42,#REF!,4,0),0) -> 0 | S42: =IFERROR(VLOOKUP(D42,#REF!,4,0),0) -> 0 | T42: =IFERROR(VLOOKUP(D42,#REF!,4,0),0) -> 0
A43: =VLOOKUP(INVENTARIO!$D43,LISTA!$A:$E,3,0) -> APC-FQ | B43: =VLOOKUP(INVENTARIO!$D43,LISTA!$A:$E,4,0) -> BEBIDAS INSTANTANEAS | C43: =VLOOKUP(INVENTARIO!$D43,LISTA!$A:$E,5,0) -> KONGA | D43: Q140 | E43: KONGA SABOR TIZANA 30GX8X14UN | F43: 14 | G43: =Q43 -> 0 | H43: =G43*F43 -> 0 | K43: =R43 -> 0 | M43: =S43 -> 0 | P43: =H43-J43-I43-K43-L43-M43-INVENTARIO!$N43-O43 -> 0 | Q43: =IFERROR(VLOOKUP(D43,'TABL COMPR'!$A:$D,4,0),0) -> 0 | R43: =IFERROR(VLOOKUP(D43,#REF!,4,0),0) -> 0 | S43: =IFERROR(VLOOKUP(D43,#REF!,4,0),0) -> 0 | T43: =IFERROR(VLOOKUP(D43,#REF!,4,0),0) -> 0
A44: =VLOOKUP(INVENTARIO!$D44,LISTA!$A:$E,3,0) -> APC-FQ | B44: =VLOOKUP(INVENTARIO!$D44,LISTA!$A:$E,4,0) -> AVENAS | C44: =VLOOKUP(INVENTARIO!$D44,LISTA!$A:$E,5,0) -> QUAKER | D44: Q137 | E44: QUAKER AVENA ORIGINAL BOLSA 200Gx30UN | F44: 30 | G44: =Q44 -> 0 | H44: =G44*F44 -> 0 | K44: =R44 -> 0 | M44: =S44 -> 0 | P44: =H44-J44-I44-K44-L44-M44-INVENTARIO!$N44-O44 -> 0 | Q44: =IFERROR(VLOOKUP(D44,'TABL COMPR'!$A:$D,4,0),0) -> 0 | R44: =IFERROR(VLOOKUP(D44,#REF!,4,0),0) -> 0 | S44: =IFERROR(VLOOKUP(D44,#REF!,4,0),0) -> 0 | T44: =IFERROR(VLOOKUP(D44,#REF!,4,0),0) -> 0
A45: =VLOOKUP(INVENTARIO!$D45,LISTA!$A:$E,3,0) -> APC-FQ | B45: =VLOOKUP(INVENTARIO!$D45,LISTA!$A:$E,4,0) -> BEBIDAS INSTANTANEAS | C45: =VLOOKUP(INVENTARIO!$D45,LISTA!$A:$E,5,0) -> KONGA | D45: Q123 | E45: KONGA SABOR PARCHITA 30GX8X14UN | F45: 14 | G45: =Q45 -> 0 | H45: =G45*F45 -> 0 | K45: =R45 -> 0 | M45: =S45 -> 0 | P45: =H45-J45-I45-K45-L45-M45-INVENTARIO!$N45-O45 -> 0 | Q45: =IFERROR(VLOOKUP(D45,'TABL COMPR'!$A:$D,4,0),0) -> 0 | R45: =IFERROR(VLOOKUP(D45,#REF!,4,0),0) -> 0 | S45: =IFERROR(VLOOKUP(D45,#REF!,4,0),0) -> 0 | T45: =IFERROR(VLOOKUP(D45,#REF!,4,0),0) -> 0
A46: =VLOOKUP(INVENTARIO!$D46,LISTA!$A:$E,3,0) -> APC-FQ | B46: =VLOOKUP(INVENTARIO!$D46,LISTA!$A:$E,4,0) -> BEBIDAS INSTANTANEAS | C46: =VLOOKUP(INVENTARIO!$D46,LISTA!$A:$E,5,0) -> KONGA | D46: Q114 | E46: KONGA SABOR NARANJA 30GX8X14UN | F46: 14 | G46: =Q46 -> 0 | H46: =G46*F46 -> 0 | K46: =R46 -> 0 | M46: =S46 -> 0 | P46: =H46-J46-I46-K46-L46-M46-INVENTARIO!$N46-O46 -> 0 | Q46: =IFERROR(VLOOKUP(D46,'TABL COMPR'!$A:$D,4,0),0) -> 0 | R46: =IFERROR(VLOOKUP(D46,#REF!,4,0),0) -> 0 | S46: =IFERROR(VLOOKUP(D46,#REF!,4,0),0) -> 0 | T46: =IFERROR(VLOOKUP(D46,#REF!,4,0),0) -> 0
A47: =VLOOKUP(INVENTARIO!$D47,LISTA!$A:$E,3,0) -> APC-FQ | B47: =VLOOKUP(INVENTARIO!$D47,LISTA!$A:$E,4,0) -> BEBIDAS INSTANTANEAS | C47: =VLOOKUP(INVENTARIO!$D47,LISTA!$A:$E,5,0) -> KONGA | D47: Q113 | E47: KONGA SABOR LIMON 30GX8X14UN | F47: 14 | G47: =Q47 -> 0 | H47: =G47*F47 -> 0 | K47: =R47 -> 0 | M47: =S47 -> 0 | P47: =H47-J47-I47-K47-L47-M47-INVENTARIO!$N47-O47 -> 0 | Q47: =IFERROR(VLOOKUP(D47,'TABL COMPR'!$A:$D,4,0),0) -> 0 | R47: =IFERROR(VLOOKUP(D47,#REF!,4,0),0) -> 0 | S47: =IFERROR(VLOOKUP(D47,#REF!,4,0),0) -> 0 | T47: =IFERROR(VLOOKUP(D47,#REF!,4,0),0) -> 0
A48: =VLOOKUP(INVENTARIO!$D48,LISTA!$A:$E,3,0) -> APC-FQ | B48: =VLOOKUP(INVENTARIO!$D48,LISTA!$A:$E,4,0) -> AVENAS | C48: =VLOOKUP(INVENTARIO!$D48,LISTA!$A:$E,5,0) -> QUAKER | D48: Q023 | E48: QUAKER HARINA DE AVENA (BOLS) 400Gx24UN | F48: 24 | G48: =Q48 -> 0 | H48: =G48*F48 -> 0 | K48: =R48 -> 0 | M48: =S48 -> 0 | P48: =H48-J48-I48-K48-L48-M48-INVENTARIO!$N48-O48 -> 0 | Q48: =IFERROR(VLOOKUP(D48,'TABL COMPR'!$A:$D,4,0),0) -> 0 | R48: =IFERROR(VLOOKUP(D48,#REF!,4,0),0) -> 0 | S48: =IFERROR(VLOOKUP(D48,#REF!,4,0),0) -> 0 | T48: =IFERROR(VLOOKUP(D48,#REF!,4,0),0) -> 0
A49: =VLOOKUP(INVENTARIO!$D49,LISTA!$A:$E,3,0) -> APC-FQ | B49: =VLOOKUP(INVENTARIO!$D49,LISTA!$A:$E,4,0) -> AVENAS | C49: =VLOOKUP(INVENTARIO!$D49,LISTA!$A:$E,5,0) -> QUAKER | D49: Q001 | E49: QUAKER AVENA ORIGINAL BOLSA 400Gx24UN | F49: 24 | G49: =Q49 -> 0 | H49: =G49*F49 -> 0 | K49: =R49 -> 0 | M49: =S49 -> 0 | P49: =H49-J49-I49-K49-L49-M49-INVENTARIO!$N49-O49 -> 0 | Q49: =IFERROR(VLOOKUP(D49,'TABL COMPR'!$A:$D,4,0),0) -> 0 | R49: =IFERROR(VLOOKUP(D49,#REF!,4,0),0) -> 0 | S49: =IFERROR(VLOOKUP(D49,#REF!,4,0),0) -> 0 | T49: =IFERROR(VLOOKUP(D49,#REF!,4,0),0) -> 0
... A159: =VLOOKUP(INVENTARIO!$D159,LISTA!$A:$E,3,0) -> APC-FQ | B159: =VLOOKUP(INVENTARIO!$D159,LISTA!$A:$E,4,0) -> CAFE | C159: =VLOOKUP(INVENTARIO!$D159,LISTA!$A:$E,5,0) -> BUEN CAFE | D159: C213 | E159: BUEN CAFE PREMIUM 500Gx10UN | F159: 10 | G159: =Q159 -> 0 | H159: =G159*F159 -> 0 | K159: =R159 -> 0 | M159: =S159 -> 0 | P159: =H159-J159-I159-K159-L159-M159-INVENTARIO!$N159-O159 -> 0 | Q159: =IFERROR(VLOOKUP(D159,'TABL COMPR'!$A:$D,4,0),0) -> 0 | R159: =IFERROR(VLOOKUP(D159,#REF!,4,0),0) -> 0 | S159: =IFERROR(VLOOKUP(D159,#REF!,4,0),0) -> 0 | T159: =IFERROR(VLOOKUP(D159,#REF!,4,0),0) -> 0
A160: =VLOOKUP(INVENTARIO!$D160,LISTA!$A:$E,3,0) -> CYM-FQ | B160: =VLOOKUP(INVENTARIO!$D160,LISTA!$A:$E,4,0) -> Light | C160: =VLOOKUP(INVENTARIO!$D160,LISTA!$A:$E,5,0) -> Polar Light | D160: F04005 | E160: POLAR LIGHT RET 222MLx36UN | F160: 36 | G160: =Q160 -> 0 | H160: =G160 -> 0 | K160: =R160 -> 0 | M160: =S160 -> 0 | P160: =H160-J160-I160-K160-L160-M160-INVENTARIO!$N160-O160 -> 0 | Q160: =IFERROR(VLOOKUP(D160,'TABL COMPR'!$A:$D,4,0),0) -> 0 | R160: =IFERROR(VLOOKUP(D160,#REF!,4,0),0) -> 0 | S160: =IFERROR(VLOOKUP(D160,#REF!,4,0),0) -> 0 | T160: =IFERROR(VLOOKUP(D160,#REF!,4,0),0) -> 0
A161: =VLOOKUP(INVENTARIO!$D161,LISTA!$A:$E,3,0) -> CYM-FQ | B161: =VLOOKUP(INVENTARIO!$D161,LISTA!$A:$E,4,0) -> Light | C161: =VLOOKUP(INVENTARIO!$D161,LISTA!$A:$E,5,0) -> Solera Light | D161: F03016 | E161: SOLERA LIGHT LAT 250MLx24UN | F161: 24 | G161: =Q161 -> 0 | H161: =G161 -> 0 | K161: =R161 -> 0 | M161: =S161 -> 0 | P161: =H161-J161-I161-K161-L161-M161-INVENTARIO!$N161-O161 -> 0 | Q161: =IFERROR(VLOOKUP(D161,'TABL COMPR'!$A:$D,4,0),0) -> 0 | R161: =IFERROR(VLOOKUP(D161,#REF!,4,0),0) -> 0 | S161: =IFERROR(VLOOKUP(D161,#REF!,4,0),0) -> 0 | T161: =IFERROR(VLOOKUP(D161,#REF!,4,0),0) -> 0
A162: CYM-FQ | B162: Light | C162: Solera Light | D162: F03090 | E162: SOLERA LIGHT LAT SLEEK 355MLX24UN | F162: 24 | G162: =Q162 -> 0 | H162: =G162 -> 0 | K162: =R162 -> 0 | M162: =S162 -> 0 | P162: =H162-J162-I162-K162-L162-M162-INVENTARIO!$N162-O162 -> 0 | Q162: =IFERROR(VLOOKUP(D162,'TABL COMPR'!$A:$D,4,0),0) -> 0 | R162: =IFERROR(VLOOKUP(D162,#REF!,4,0),0) -> 0 | S162: =IFERROR(VLOOKUP(D162,#REF!,4,0),0) -> 0 | T162: =IFERROR(VLOOKUP(D162,#REF!,4,0),0) -> 0
A163: =VLOOKUP(INVENTARIO!$D163,LISTA!$A:$E,3,0) -> CYM-FQ | B163: =VLOOKUP(INVENTARIO!$D163,LISTA!$A:$E,4,0) -> Tradicional | C163: =VLOOKUP(INVENTARIO!$D163,LISTA!$A:$E,5,0) -> Polar Pilsen | D163: F01001 | E163: POLAR PILSEN RET 222MLx36UN | F163: 36 | G163: =Q163 -> 0 | H163: =G163 -> 0 | K163: =R163 -> 0 | M163: =S163 -> 0 | P163: =H163-J163-I163-K163-L163-M163-INVENTARIO!$N163-O163 -> 0 | Q163: =IFERROR(VLOOKUP(D163,'TABL COMPR'!$A:$D,4,0),0) -> 0 | R163: =IFERROR(VLOOKUP(D163,#REF!,4,0),0) -> 0 | S163: =IFERROR(VLOOKUP(D163,#REF!,4,0),0) -> 0 | T163: =IFERROR(VLOOKUP(D163,#REF!,4,0),0) -> 0
A164: =VLOOKUP(INVENTARIO!$D164,LISTA!$A:$E,3,0) -> CYM-FQ | B164: =VLOOKUP(INVENTARIO!$D164,LISTA!$A:$E,4,0) -> Premiun | C164: =VLOOKUP(INVENTARIO!$D164,LISTA!$A:$E,5,0) -> Solera | D164: F03030 | E164: SOLERA RET 222MLx36UN | F164: 36 | G164: =Q164 -> 0 | H164: =G164 -> 0 | K164: =R164 -> 0 | M164: =S164 -> 0 | P164: =H164-J164-I164-K164-L164-M164-INVENTARIO!$N164-O164 -> 0 | Q164: =IFERROR(VLOOKUP(D164,'TABL COMPR'!$A:$D,4,0),0) -> 0 | R164: =IFERROR(VLOOKUP(D164,#REF!,4,0),0) -> 0 | S164: =IFERROR(VLOOKUP(D164,#REF!,4,0),0) -> 0 | T164: =IFERROR(VLOOKUP(D164,#REF!,4,0),0) -> 0
A165: =VLOOKUP(INVENTARIO!$D165,LISTA!$A:$E,3,0) -> CYM-FQ | B165: =VLOOKUP(INVENTARIO!$D165,LISTA!$A:$E,4,0) -> Premiun | C165: =VLOOKUP(INVENTARIO!$D165,LISTA!$A:$E,5,0) -> Solera Alt | D165: F06068 | E165: SOLERA BOHEMIA LAT 250MLx24UN | F165: 24 | G165: =Q165 -> 0 | H165: =INVENTARIO!$G165 -> 0 | K165: =R165 -> 0 | M165: =S165 -> 0 | P165: =H165-J165-I165-K165-L165-M165-INVENTARIO!$N165-O165 -> 0 | Q165: =IFERROR(VLOOKUP(D165,'TABL COMPR'!$A:$D,4,0),0) -> 0 | R165: =IFERROR(VLOOKUP(D165,#REF!,4,0),0) -> 0 | S165: =IFERROR(VLOOKUP(D165,#REF!,4,0),0) -> 0 | T165: =IFERROR(VLOOKUP(D165,#REF!,4,0),0) -> 0
A166: =VLOOKUP(INVENTARIO!$D166,LISTA!$A:$E,3,0) -> CYM-FQ | B166: =VLOOKUP(INVENTARIO!$D166,LISTA!$A:$E,4,0) -> Premiun | C166: =VLOOKUP(INVENTARIO!$D166,LISTA!$A:$E,5,0) -> Solera | D166: F03001 | E166: SOLERA LAT 250MLx24UN | F166: 24 | G166: =Q166 -> 0 | H166: =G166 -> 0 | K166: =R166 -> 0 | M166: =S166 -> 0 | P166: =H166-J166-I166-K166-L166-M166-INVENTARIO!$N166-O166 -> 0 | Q166: =IFERROR(VLOOKUP(D166,'TABL COMPR'!$A:$D,4,0),0) -> 0 | R166: =IFERROR(VLOOKUP(D166,#REF!,4,0),0) -> 0 | S166: =IFERROR(VLOOKUP(D166,#REF!,4,0),0) -> 0 | T166: =IFERROR(VLOOKUP(D166,#REF!,4,0),0) -> 0
A167: =VLOOKUP(INVENTARIO!$D167,LISTA!$A:$E,3,0) -> CYM-FQ | B167: =VLOOKUP(INVENTARIO!$D167,LISTA!$A:$E,4,0) -> Light | C167: =VLOOKUP(INVENTARIO!$D167,LISTA!$A:$E,5,0) -> Polar Light | D167: F04014 | E167: POLAR LIGHT LAT 250MLx24UN | F167: 24 | G167: =Q167 -> 0 | H167: =G167 -> 0 | K167: =R167 -> 0 | M167: =S167 -> 0 | P167: =H167-J167-I167-K167-L167-M167-INVENTARIO!$N167-O167 -> 0 | Q167: =IFERROR(VLOOKUP(D167,'TABL COMPR'!$A:$D,4,0),0) -> 0 | R167: =IFERROR(VLOOKUP(D167,#REF!,4,0),0) -> 0 | S167: =IFERROR(VLOOKUP(D167,#REF!,4,0),0) -> 0 | T167: =IFERROR(VLOOKUP(D167,#REF!,4,0),0) -> 0
A168: =VLOOKUP(INVENTARIO!$D168,LISTA!$A:$E,3,0) -> CYM-FQ | B168: =VLOOKUP(INVENTARIO!$D168,LISTA!$A:$E,4,0) -> Sangría | C168: =VLOOKUP(INVENTARIO!$D168,LISTA!$A:$E,5,0) -> Caroreña | D168: FR0159 | E168: SANGRIA CAROREÑA VERANO MOJITO LAT355x24 | F168: 24 | G168: =Q168 -> 0 | H168: =G168*F168 -> 0 | K168: =R168 -> 0 | M168: =S168 -> 0 | P168: =H168-J168-I168-K168-L168-M168-INVENTARIO!$N168-O168 -> 0 | Q168: =IFERROR(VLOOKUP(D168,'TABL COMPR'!$A:$D,4,0),0) -> 0 | R168: =IFERROR(VLOOKUP(D168,#REF!,4,0),0) -> 0 | S168: =IFERROR(VLOOKUP(D168,#REF!,4,0),0) -> 0 | T168: =IFERROR(VLOOKUP(D168,#REF!,4,0),0) -> 0
A169: =VLOOKUP(INVENTARIO!$D169,LISTA!$A:$E,3,0) -> CYM-FQ | B169: =VLOOKUP(INVENTARIO!$D169,LISTA!$A:$E,4,0) -> Sangría | C169: =VLOOKUP(INVENTARIO!$D169,LISTA!$A:$E,5,0) -> Caroreña | D169: FR0154 | E169: SANGRIA CAROREÑA VERANO MOJITO LAT355x12 | F169: 12 | G169: =Q169 -> 0 | H169: =G169 -> 0 | K169: =R169 -> 0 | M169: =S169 -> 0 | P169: =H169-J169-I169-K169-L169-M169-INVENTARIO!$N169-O169 -> 0 | Q169: =IFERROR(VLOOKUP(D169,'TABL COMPR'!$A:$D,4,0),0) -> 0 | R169: =IFERROR(VLOOKUP(D169,#REF!,4,0),0) -> 0 | S169: =IFERROR(VLOOKUP(D169,#REF!,4,0),0) -> 0 | T169: =IFERROR(VLOOKUP(D169,#REF!,4,0),0) -> 0
A170: =VLOOKUP(INVENTARIO!$D170,LISTA!$A:$E,3,0) -> CYM-FQ | B170: =VLOOKUP(INVENTARIO!$D170,LISTA!$A:$E,4,0) -> Sangría | C170: =VLOOKUP(INVENTARIO!$D170,LISTA!$A:$E,5,0) -> Caroreña | D170: FR0153 | E170: SANGRIA CAROREÑA VERANO BLANCA LAT250X12 | F170: 12 | G170: =Q170 -> 0 | H170: =G170 -> 0 | K170: =R170 -> 0 | M170: =S170 -> 0 | P170: =H170-J170-I170-K170-L170-M170-INVENTARIO!$N170-O170 -> 0 | Q170: =IFERROR(VLOOKUP(D170,'TABL COMPR'!$A:$D,4,0),0) -> 0 | R170: =IFERROR(VLOOKUP(D170,#REF!,4,0),0) -> 0 | S170: =IFERROR(VLOOKUP(D170,#REF!,4,0),0) -> 0 | T170: =IFERROR(VLOOKUP(D170,#REF!,4,0),0) -> 0
A171: =VLOOKUP(INVENTARIO!$D171,LISTA!$A:$E,3,0) -> CYM-FQ | B171: =VLOOKUP(INVENTARIO!$D171,LISTA!$A:$E,4,0) -> Sangría | C171: =VLOOKUP(INVENTARIO!$D171,LISTA!$A:$E,5,0) -> Caroreña | D171: FR0137 | E171: SANGRIA CAROREÑA VERANO LAT250MLx12UN | F171: 12 | G171: =Q171 -> 0 | H171: =G171 -> 0 | K171: =R171 -> 0 | M171: =S171 -> 0 | P171: =H171-J171-I171-K171-L171-M171-INVENTARIO!$N171-O171 -> 0 | Q171: =IFERROR(VLOOKUP(D171,'TABL COMPR'!$A:$D,4,0),0) -> 0 | R171: =IFERROR(VLOOKUP(D171,#REF!,4,0),0) -> 0 | S171: =IFERROR(VLOOKUP(D171,#REF!,4,0),0) -> 0 | T171: =IFERROR(VLOOKUP(D171,#REF!,4,0),0) -> 0
A172: =VLOOKUP(INVENTARIO!$D172,LISTA!$A:$E,3,0) -> CYM-FQ | B172: =VLOOKUP(INVENTARIO!$D172,LISTA!$A:$E,4,0) -> Sangría | C172: =VLOOKUP(INVENTARIO!$D172,LISTA!$A:$E,5,0) -> Caroreña | D172: FR0123 | E172: SANGRIA CAROREÑA ROSADA 1,75Lx6UN | F172: 6 | G172: =Q172 -> 0 | H172: =G172 -> 0 | K172: =R172 -> 0 | M172: =S172 -> 0 | P172: =H172-J172-I172-K172-L172-M172-INVENTARIO!$N172-O172 -> 0 | Q172: =IFERROR(VLOOKUP(D172,'TABL COMPR'!$A:$D,4,0),0) -> 0 | R172: =IFERROR(VLOOKUP(D172,#REF!,4,0),0) -> 0 | S172: =IFERROR(VLOOKUP(D172,#REF!,4,0),0) -> 0 | T172: =IFERROR(VLOOKUP(D172,#REF!,4,0),0) -> 0
A173: =VLOOKUP(INVENTARIO!$D173,LISTA!$A:$E,3,0) -> CYM-FQ | B173: =VLOOKUP(INVENTARIO!$D173,LISTA!$A:$E,4,0) -> Sangría | C173: =VLOOKUP(INVENTARIO!$D173,LISTA!$A:$E,5,0) -> La Que Manda | D173: FR0145 | E173: SANGRIA LA QUE MANDA BLANCA 1,75LX6UN | F173: 6 | G173: =Q173 -> 0 | H173: =G173 -> 0 | K173: =R173 -> 0 | M173: =S173 -> 0 | P173: =H173-J173-I173-K173-L173-M173-INVENTARIO!$N173-O173 -> 0 | Q173: =IFERROR(VLOOKUP(D173,'TABL COMPR'!$A:$D,4,0),0) -> 0 | R173: =IFERROR(VLOOKUP(D173,#REF!,4,0),0) -> 0 | S173: =IFERROR(VLOOKUP(D173,#REF!,4,0),0) -> 0 | T173: =IFERROR(VLOOKUP(D173,#REF!,4,0),0) -> 0
A174: =VLOOKUP(INVENTARIO!$D174,LISTA!$A:$E,3,0) -> CYM-FQ | B174: =VLOOKUP(INVENTARIO!$D174,LISTA!$A:$E,4,0) -> Malta | C174: =VLOOKUP(INVENTARIO!$D174,LISTA!$A:$E,5,0) -> Maltin Polar | D174: F07018 | E174: MALTIN POLAR PET 1.5 Lx6UN | F174: 6 | G174: =Q174 -> 0 | H174: =G174 -> 0 | K174: =R174 -> 0 | M174: =S174 -> 0 | P174: =H174-J174-I174-K174-L174-M174-INVENTARIO!$N174-O174 -> 0 | Q174: =IFERROR(VLOOKUP(D174,'TABL COMPR'!$A:$D,4,0),0) -> 0 | R174: =IFERROR(VLOOKUP(D174,#REF!,4,0),0) -> 0 | S174: =IFERROR(VLOOKUP(D174,#REF!,4,0),0) -> 0 | T174: =IFERROR(VLOOKUP(D174,#REF!,4,0),0) -> 0
A175: =VLOOKUP(INVENTARIO!$D175,LISTA!$A:$E,3,0) -> CYM-FQ | B175: =VLOOKUP(INVENTARIO!$D175,LISTA!$A:$E,4,0) -> Malta | C175: =VLOOKUP(INVENTARIO!$D175,LISTA!$A:$E,5,0) -> Maltin Polar | D175: F07101 | E175: MALTIN POLAR LAT SLEEK 355MLx24UN | F175: 24 | G175: =Q175 -> 0 | H175: =G175*F175 -> 0 | K175: =R175 -> 0 | M175: =S175 -> 0 | P175: =H175-J175-I175-K175-L175-M175-INVENTARIO!$N175-O175 -> 0 | Q175: =IFERROR(VLOOKUP(D175,'TABL COMPR'!$A:$D,4,0),0) -> 0 | R175: =IFERROR(VLOOKUP(D175,#REF!,4,0),0) -> 0 | S175: =IFERROR(VLOOKUP(D175,#REF!,4,0),0) -> 0 | T175: =IFERROR(VLOOKUP(D175,#REF!,4,0),0) -> 0
A176: =VLOOKUP(INVENTARIO!$D176,LISTA!$A:$E,3,0) -> CYM-FQ | B176: =VLOOKUP(INVENTARIO!$D176,LISTA!$A:$E,4,0) -> Premiun | C176: =VLOOKUP(INVENTARIO!$D176,LISTA!$A:$E,5,0) -> Solera | D176: F03063 | E176: SOLERA LAT 250MLx12UN | F176: 12 | G176: =Q176 -> 0 | H176: =G176 -> 0 | K176: =R176 -> 0 | M176: =S176 -> 0 | P176: =H176-J176-I176-K176-L176-M176-INVENTARIO!$N176-O176 -> 0 | Q176: =IFERROR(VLOOKUP(D176,'TABL COMPR'!$A:$D,4,0),0) -> 0 | R176: =IFERROR(VLOOKUP(D176,#REF!,4,0),0) -> 0 | S176: =IFERROR(VLOOKUP(D176,#REF!,4,0),0) -> 0 | T176: =IFERROR(VLOOKUP(D176,#REF!,4,0),0) -> 0
A177: =VLOOKUP(INVENTARIO!$D177,LISTA!$A:$E,3,0) -> CYM-FQ | B177: =VLOOKUP(INVENTARIO!$D177,LISTA!$A:$E,4,0) -> Tradicional | C177: =VLOOKUP(INVENTARIO!$D177,LISTA!$A:$E,5,0) -> Polar Pilsen | D177: F01063 | E177: POLAR PILSEN NR 355MLx12UN | F177: 12 | G177: =Q177 -> 0 | H177: =G177 -> 0 | K177: =R177 -> 0 | M177: =S177 -> 0 | P177: =H177-J177-I177-K177-L177-M177-INVENTARIO!$N177-O177 -> 0 | Q177: =IFERROR(VLOOKUP(D177,'TABL COMPR'!$A:$D,4,0),0) -> 0 | R177: =IFERROR(VLOOKUP(D177,#REF!,4,0),0) -> 0 | S177: =IFERROR(VLOOKUP(D177,#REF!,4,0),0) -> 0 | T177: =IFERROR(VLOOKUP(D177,#REF!,4,0),0) -> 0
A178: =VLOOKUP(INVENTARIO!$D178,LISTA!$A:$E,3,0) -> CYM-FQ | B178: =VLOOKUP(INVENTARIO!$D178,LISTA!$A:$E,4,0) -> Sangría | C178: =VLOOKUP(INVENTARIO!$D178,LISTA!$A:$E,5,0) -> Caroreña | D178: FR0103 | E178: SANGRIA CAROREÑA TINTA 1,75Lx6UN | F178: 6 | G178: =Q178 -> 0 | H178: =G178 -> 0 | K178: =R178 -> 0 | M178: =S178 -> 0 | P178: =H178-J178-I178-K178-L178-M178-INVENTARIO!$N178-O178 -> 0 | Q178: =IFERROR(VLOOKUP(D178,'TABL COMPR'!$A:$D,4,0),0) -> 0 | R178: =IFERROR(VLOOKUP(D178,#REF!,4,0),0) -> 0 | S178: =IFERROR(VLOOKUP(D178,#REF!,4,0),0) -> 0 | T178: =IFERROR(VLOOKUP(D178,#REF!,4,0),0) -> 0
A179: =VLOOKUP(INVENTARIO!$D179,LISTA!$A:$E,3,0) -> CYM-FQ | B179: =VLOOKUP(INVENTARIO!$D179,LISTA!$A:$E,4,0) -> Light | C179: =VLOOKUP(INVENTARIO!$D179,LISTA!$A:$E,5,0) -> Solera Light | D179: F03014 | E179: SOLERA LIGHT RET 222MLx36UN | F179: 36 | G179: =Q179 -> 0 | H179: =G179 -> 0 | K179: =R179 -> 0 | M179: =S179 -> 0 | P179: =H179-J179-I179-K179-L179-M179-INVENTARIO!$N179-O179 -> 0 | Q179: =IFERROR(VLOOKUP(D179,'TABL COMPR'!$A:$D,4,0),0) -> 0 | R179: =IFERROR(VLOOKUP(D179,#REF!,4,0),0) -> 0 | S179: =IFERROR(VLOOKUP(D179,#REF!,4,0),0) -> 0 | T179: =IFERROR(VLOOKUP(D179,#REF!,4,0),0) -> 0
A180: =VLOOKUP(INVENTARIO!$D180,LISTA!$A:$E,3,0) -> CYM-FQ | B180: =VLOOKUP(INVENTARIO!$D180,LISTA!$A:$E,4,0) -> Tradicional | C180: =VLOOKUP(INVENTARIO!$D180,LISTA!$A:$E,5,0) -> Polar Pilsen | D180: F01002 | E180: POLAR PILSEN RET 330MLx24UN | F180: 24 | G180: =Q180 -> 0 | H180: =G180 -> 0 | K180: =R180 -> 0 | M180: =S180 -> 0 | P180: =H180-J180-I180-K180-L180-M180-INVENTARIO!$N180-O180 -> 0 | Q180: =IFERROR(VLOOKUP(D180,'TABL COMPR'!$A:$D,4,0),0) -> 0 | R180: =IFERROR(VLOOKUP(D180,#REF!,4,0),0) -> 0 | S180: =IFERROR(VLOOKUP(D180,#REF!,4,0),0) -> 0 | T180: =IFERROR(VLOOKUP(D180,#REF!,4,0),0) -> 0
A181: =VLOOKUP(INVENTARIO!$D181,LISTA!$A:$E,3,0) -> CYM-FQ | B181: =VLOOKUP(INVENTARIO!$D181,LISTA!$A:$E,4,0) -> Malta | C181: =VLOOKUP(INVENTARIO!$D181,LISTA!$A:$E,5,0) -> Maltin Polar | D181: F07001 | E181: MALTIN POLAR RET 222MLx36UN | F181: 36 | G181: =Q181 -> 0 | H181: =G181 -> 0 | K181: =R181 -> 0 | M181: =S181 -> 0 | P181: =H181-J181-I181-K181-L181-M181-INVENTARIO!$N181-O181 -> 0 | Q181: =IFERROR(VLOOKUP(D181,'TABL COMPR'!$A:$D,4,0),0) -> 0 | R181: =IFERROR(VLOOKUP(D181,#REF!,4,0),0) -> 0 | S181: =IFERROR(VLOOKUP(D181,#REF!,4,0),0) -> 0 | T181: =IFERROR(VLOOKUP(D181,#REF!,4,0),0) -> 0
A182: =VLOOKUP(INVENTARIO!$D182,LISTA!$A:$E,3,0) -> CYM-FQ | B182: =VLOOKUP(INVENTARIO!$D182,LISTA!$A:$E,4,0) -> Tradicional | C182: =VLOOKUP(INVENTARIO!$D182,LISTA!$A:$E,5,0) -> Polar Pilsen | D182: F01003 | E182: POLAR PILSEN LAT 250MLx24UN | F182: 24 | G182: =Q182 -> 0 | H182: =G182 -> 0 | K182: =R182 -> 0 | M182: =S182 -> 0 | P182: =H182-J182-I182-K182-L182-M182-INVENTARIO!$N182-O182 -> 0 | Q182: =IFERROR(VLOOKUP(D182,'TABL COMPR'!$A:$D,4,0),0) -> 0 | R182: =IFERROR(VLOOKUP(D182,#REF!,4,0),0) -> 0 | S182: =IFERROR(VLOOKUP(D182,#REF!,4,0),0) -> 0 | T182: =IFERROR(VLOOKUP(D182,#REF!,4,0),0) -> 0
A183: =VLOOKUP(INVENTARIO!$D183,LISTA!$A:$E,3,0) -> CYM-FQ | B183: =VLOOKUP(INVENTARIO!$D183,LISTA!$A:$E,4,0) -> Malta | C183: =VLOOKUP(INVENTARIO!$D183,LISTA!$A:$E,5,0) -> Maltin Polar | D183: F07007 | E183: MALTIN POLAR LAT 250MLx24UN | F183: 24 | G183: =Q183 -> 0 | H183: =G183 -> 0 | K183: =R183 -> 0 | M183: =S183 -> 0 | P183: =H183-J183-I183-K183-L183-M183-INVENTARIO!$N183-O183 -> 0 | Q183: =IFERROR(VLOOKUP(D183,'TABL COMPR'!$A:$D,4,0),0) -> 0 | R183: =IFERROR(VLOOKUP(D183,#REF!,4,0),0) -> 0 | S183: =IFERROR(VLOOKUP(D183,#REF!,4,0),0) -> 0 | T183: =IFERROR(VLOOKUP(D183,#REF!,4,0),0) -> 0
A184: =VLOOKUP(INVENTARIO!$D184,LISTA!$A:$E,3,0) -> CYM-FQ | B184: =VLOOKUP(INVENTARIO!$D184,LISTA!$A:$E,4,0) -> Sangría | C184: =VLOOKUP(INVENTARIO!$D184,LISTA!$A:$E,5,0) -> La Que Manda | D184: FR0141 | E184: SANGRIA LA QUE MANDA TINTA 1,75LX6UN | F184: 6 | G184: =Q184 -> 0 | H184: =G184 -> 0 | K184: =R184 -> 0 | M184: =S184 -> 0 | P184: =H184-J184-I184-K184-L184-M184-INVENTARIO!$N184-O184 -> 0 | Q184: =IFERROR(VLOOKUP(D184,'TABL COMPR'!$A:$D,4,0),0) -> 0 | R184: =IFERROR(VLOOKUP(D184,#REF!,4,0),0) -> 0 | S184: =IFERROR(VLOOKUP(D184,#REF!,4,0),0) -> 0 | T184: =IFERROR(VLOOKUP(D184,#REF!,4,0),0) -> 0
A185: =VLOOKUP(INVENTARIO!$D185,LISTA!$A:$E,3,0) -> CYM-FQ | B185: =VLOOKUP(INVENTARIO!$D185,LISTA!$A:$E,4,0) -> Sangría | C185: =VLOOKUP(INVENTARIO!$D185,LISTA!$A:$E,5,0) -> Caroreña | D185: FR0158 | E185: SANGRIA CAROREÑA VERANO BLANCA LAT250X24 | F185: 24 | G185: =Q185 -> 0 | H185: =G185*F185 -> 0 | K185: =R185 -> 0 | M185: =S185 -> 0 | P185: =H185-J185-I185-K185-L185-M185-INVENTARIO!$N185-O185 -> 0 | Q185: =IFERROR(VLOOKUP(D185,'TABL COMPR'!$A:$D,4,0),0) -> 0 | R185: =IFERROR(VLOOKUP(D185,#REF!,4,0),0) -> 0 | S185: =IFERROR(VLOOKUP(D185,#REF!,4,0),0) -> 0 | T185: =IFERROR(VLOOKUP(D185,#REF!,4,0),0) -> 0
A186: =VLOOKUP(INVENTARIO!$D186,LISTA!$A:$E,3,0) -> CYM-FQ | B186: =VLOOKUP(INVENTARIO!$D186,LISTA!$A:$E,4,0) -> Sangría | C186: =VLOOKUP(INVENTARIO!$D186,LISTA!$A:$E,5,0) -> La Que Manda | D186: FR0160 | E186: SANGRIA LA QUE MANDA TINTA LAT250MLx24UN | F186: 24 | G186: =Q186 -> 0 | H186: =G186*F186 -> 0 | K186: =R186 -> 0 | M186: =S186 -> 0 | P186: =H186-J186-I186-K186-L186-M186-INVENTARIO!$N186-O186 -> 0 | Q186: =IFERROR(VLOOKUP(D186,'TABL COMPR'!$A:$D,4,0),0) -> 0 | R186: =IFERROR(VLOOKUP(D186,#REF!,4,0),0) -> 0 | S186: =IFERROR(VLOOKUP(D186,#REF!,4,0),0) -> 0 | T186: =IFERROR(VLOOKUP(D186,#REF!,4,0),0) -> 0
A187: =VLOOKUP(INVENTARIO!$D187,LISTA!$A:$E,3,0) -> CYM-FQ | B187: =VLOOKUP(INVENTARIO!$D187,LISTA!$A:$E,4,0) -> Light | C187: =VLOOKUP(INVENTARIO!$D187,LISTA!$A:$E,5,0) -> Polar Light | D187: F04061 | E187: POLAR LIGHT LAT SLEEK 355MLx24UN | F187: 24 | G187: =Q187 -> 0 | H187: =G187 -> 0 | K187: =R187 -> 0 | M187: =S187 -> 0 | P187: =H187-J187-I187-K187-L187-M187-INVENTARIO!$N187-O187 -> 0 | Q187: =IFERROR(VLOOKUP(D187,'TABL COMPR'!$A:$D,4,0),0) -> 0 | R187: =IFERROR(VLOOKUP(D187,#REF!,4,0),0) -> 0 | S187: =IFERROR(VLOOKUP(D187,#REF!,4,0),0) -> 0 | T187: =IFERROR(VLOOKUP(D187,#REF!,4,0),0) -> 0
A188: =VLOOKUP(INVENTARIO!$D188,LISTA!$A:$E,3,0) -> CYM-FQ | B188: =VLOOKUP(INVENTARIO!$D188,LISTA!$A:$E,4,0) -> Sangría | C188: =VLOOKUP(INVENTARIO!$D188,LISTA!$A:$E,5,0) -> Caroreña | D188: FR0120 | E188: SANGRIA CAROREÑA BLANCA 1,75Lx6UN | F188: 6 | G188: =Q188 -> 0 | H188: =G188 -> 0 | K188: =R188 -> 0 | M188: =S188 -> 0 | P188: =H188-J188-I188-K188-L188-M188-INVENTARIO!$N188-O188 -> 0 | Q188: =IFERROR(VLOOKUP(D188,'TABL COMPR'!$A:$D,4,0),0) -> 0 | R188: =IFERROR(VLOOKUP(D188,#REF!,4,0),0) -> 0 | S188: =IFERROR(VLOOKUP(D188,#REF!,4,0),0) -> 0 | T188: =IFERROR(VLOOKUP(D188,#REF!,4,0),0) -> 0
A189: =VLOOKUP(INVENTARIO!$D189,LISTA!$A:$E,3,0) -> CYM-FQ | B189: =VLOOKUP(INVENTARIO!$D189,LISTA!$A:$E,4,0) -> Sangría | C189: =VLOOKUP(INVENTARIO!$D189,LISTA!$A:$E,5,0) -> Caroreña | D189: FR0155 | E189: SANGRIA CAROREÑA VERANO LAT250MLx24UN | F189: 24 | G189: =Q189 -> 0 | H189: =G189*F189 -> 0 | K189: =R189 -> 0 | M189: =S189 -> 0 | P189: =H189-J189-I189-K189-L189-M189-INVENTARIO!$N189-O189 -> 0 | Q189: =IFERROR(VLOOKUP(D189,'TABL COMPR'!$A:$D,4,0),0) -> 0 | R189: =IFERROR(VLOOKUP(D189,#REF!,4,0),0) -> 0 | S189: =IFERROR(VLOOKUP(D189,#REF!,4,0),0) -> 0 | T189: =IFERROR(VLOOKUP(D189,#REF!,4,0),0) -> 0
A190: =VLOOKUP(INVENTARIO!$D190,LISTA!$A:$E,3,0) -> CYM-FQ | B190: =VLOOKUP(INVENTARIO!$D190,LISTA!$A:$E,4,0) -> Tradicional | C190: =VLOOKUP(INVENTARIO!$D190,LISTA!$A:$E,5,0) -> Polar Pilsen | D190: F01083 | E190: POLAR PILSEN LAT SLEEK 355MLx24UN | F190: 24 | G190: =Q190 -> 0 | H190: =G190 -> 0 | K190: =R190 -> 0 | M190: =S190 -> 0 | P190: =H190-J190-I190-K190-L190-M190-INVENTARIO!$N190-O190 -> 0 | Q190: =IFERROR(VLOOKUP(D190,'TABL COMPR'!$A:$D,4,0),0) -> 0 | R190: =IFERROR(VLOOKUP(D190,#REF!,4,0),0) -> 0 | S190: =IFERROR(VLOOKUP(D190,#REF!,4,0),0) -> 0 | T190: =IFERROR(VLOOKUP(D190,#REF!,4,0),0) -> 0
A191: =VLOOKUP(INVENTARIO!$D191,LISTA!$A:$E,3,0) -> CYM-FQ | B191: =VLOOKUP(INVENTARIO!$D191,LISTA!$A:$E,4,0) -> Malta | C191: =VLOOKUP(INVENTARIO!$D191,LISTA!$A:$E,5,0) -> Maltin Polar | D191: F07088 | E191: MALTIN POLAR NR 250MLx12UN | F191: 12 | G191: =Q191 -> 0 | H191: =G191 -> 0 | K191: =R191 -> 0 | M191: =S191 -> 0 | P191: =H191-J191-I191-K191-L191-M191-INVENTARIO!$N191-O191 -> 0 | Q191: =IFERROR(VLOOKUP(D191,'TABL COMPR'!$A:$D,4,0),0) -> 0 | R191: =IFERROR(VLOOKUP(D191,#REF!,4,0),0) -> 0 | S191: =IFERROR(VLOOKUP(D191,#REF!,4,0),0) -> 0 | T191: =IFERROR(VLOOKUP(D191,#REF!,4,0),0) -> 0
A192: CYM-FQ | B192: Sangría | C192: Caroreña | D192: FR0162 | E192: SANGRIA CAROREÑA TORONJA 1,75Lx6UN | F192: 6 | G192: =Q192 -> 0 | H192: =G192 -> 0 | K192: =R192 -> 0 | M192: =S192 -> 0 | P192: =H192-J192-I192-K192-L192-M192-INVENTARIO!$N192-O192 -> 0 | Q192: =IFERROR(VLOOKUP(D192,'TABL COMPR'!$A:$D,4,0),0) -> 0 | R192: =IFERROR(VLOOKUP(D192,#REF!,4,0),0) -> 0 | S192: =IFERROR(VLOOKUP(D192,#REF!,4,0),0) -> 0 | T192: =IFERROR(VLOOKUP(D192,#REF!,4,0),0) -> 0
A193: =VLOOKUP(INVENTARIO!$D193,LISTA!$A:$E,3,0) -> P&G-FQ | B193: =VLOOKUP(INVENTARIO!$D193,LISTA!$A:$E,4,0) -> CUIDADOPERSONAL | C193: =VLOOKUP(INVENTARIO!$D193,LISTA!$A:$E,5,0) -> Secret | D193: 80321737 | E193: SECRET ANTIT ROLL-ON PROTECT 60GX12UN | F193: 12 | G193: =Q193 -> 0 | H193: =G193*F193 -> 0 | K193: =R193 -> 0 | M193: =S193 -> 0 | P193: =H193-J193-I193-K193-L193-M193-INVENTARIO!$N193-O193 -> 0 | Q193: =IFERROR(VLOOKUP(D193,'TABL COMPR'!$A:$D,4,0),0) -> 0 | R193: =IFERROR(VLOOKUP(D193,#REF!,4,0),0) -> 0 | S193: =IFERROR(VLOOKUP(D193,#REF!,4,0),0) -> 0 | T193: =IFERROR(VLOOKUP(D193,#REF!,4,0),0) -> 0
A194: =VLOOKUP(INVENTARIO!$D194,LISTA!$A:$E,3,0) -> P&G-FQ | B194: =VLOOKUP(INVENTARIO!$D194,LISTA!$A:$E,4,0) -> CUIDADOPERSONAL | C194: =VLOOKUP(INVENTARIO!$D194,LISTA!$A:$E,5,0) -> Old Spice | D194: 80330555 | E194: OLD SPICE SPRAY ANTIT LENA 93GX12UN | F194: 12 | G194: =Q194 -> 0 | H194: =G194*F194 -> 0 | K194: =R194 -> 0 | M194: =S194 -> 0 | P194: =H194-J194-I194-K194-L194-M194-INVENTARIO!$N194-O194 -> 0 | Q194: =IFERROR(VLOOKUP(D194,'TABL COMPR'!$A:$D,4,0),0) -> 0 | R194: =IFERROR(VLOOKUP(D194,#REF!,4,0),0) -> 0 | S194: =IFERROR(VLOOKUP(D194,#REF!,4,0),0) -> 0 | T194: =IFERROR(VLOOKUP(D194,#REF!,4,0),0) -> 0
A195: =VLOOKUP(INVENTARIO!$D195,LISTA!$A:$E,3,0) -> P&G-FQ | B195: =VLOOKUP(INVENTARIO!$D195,LISTA!$A:$E,4,0) -> AFEITADO | C195: =VLOOKUP(INVENTARIO!$D195,LISTA!$A:$E,5,0) -> Gillette UG | D195: 80685924 | E195: GILLETTE BLISTER PB3X2UN MASC 23GX72UN | F195: 72 | G195: =Q195 -> 0 | H195: =G195*F195 -> 0 | K195: =R195 -> 0 | M195: =S195 -> 0 | P195: =H195-J195-I195-K195-L195-M195-INVENTARIO!$N195-O195 -> 0 | Q195: =IFERROR(VLOOKUP(D195,'TABL COMPR'!$A:$D,4,0),0) -> 0 | R195: =IFERROR(VLOOKUP(D195,#REF!,4,0),0) -> 0 | S195: =IFERROR(VLOOKUP(D195,#REF!,4,0),0) -> 0 | T195: =IFERROR(VLOOKUP(D195,#REF!,4,0),0) -> 0
A196: =VLOOKUP(INVENTARIO!$D196,LISTA!$A:$E,3,0) -> P&G-FQ | B196: =VLOOKUP(INVENTARIO!$D196,LISTA!$A:$E,4,0) -> CUIDADO DEL CABELLO | C196: =VLOOKUP(INVENTARIO!$D196,LISTA!$A:$E,5,0) -> Pantene | D196: 80686979 | E196: PTN SHAMPOO COLAGENO 300CCX12UN | F196: 12 | G196: =Q196 -> 0 | H196: =G196*F196 -> 0 | K196: =R196 -> 0 | M196: =S196 -> 0 | P196: =H196-J196-I196-K196-L196-M196-INVENTARIO!$N196-O196 -> 0 | Q196: =IFERROR(VLOOKUP(D196,'TABL COMPR'!$A:$D,4,0),0) -> 0 | R196: =IFERROR(VLOOKUP(D196,#REF!,4,0),0) -> 0 | S196: =IFERROR(VLOOKUP(D196,#REF!,4,0),0) -> 0 | T196: =IFERROR(VLOOKUP(D196,#REF!,4,0),0) -> 0
A197: =VLOOKUP(INVENTARIO!$D197,LISTA!$A:$E,3,0) -> P&G-FQ | B197: =VLOOKUP(INVENTARIO!$D197,LISTA!$A:$E,4,0) -> CUIDADOPERSONAL | C197: =VLOOKUP(INVENTARIO!$D197,LISTA!$A:$E,5,0) -> Old Spice | D197: 80694984 | E197: OLD SPICE BARRA ANTIT FRESH 50GX12UN | F197: 12 | G197: =Q197 -> 0 | H197: =G197*F197 -> 0 | K197: =R197 -> 0 | M197: =S197 -> 0 | P197: =H197-J197-I197-K197-L197-M197-INVENTARIO!$N197-O197 -> 0 | Q197: =IFERROR(VLOOKUP(D197,'TABL COMPR'!$A:$D,4,0),0) -> 0 | R197: =IFERROR(VLOOKUP(D197,#REF!,4,0),0) -> 0 | S197: =IFERROR(VLOOKUP(D197,#REF!,4,0),0) -> 0 | T197: =IFERROR(VLOOKUP(D197,#REF!,4,0),0) -> 0
A198: =VLOOKUP(INVENTARIO!$D198,LISTA!$A:$E,3,0) -> P&G-FQ | B198: =VLOOKUP(INVENTARIO!$D198,LISTA!$A:$E,4,0) -> CUIDADO DE LA ROPA | C198: =VLOOKUP(INVENTARIO!$D198,LISTA!$A:$E,5,0) -> Ariel | D198: 80826039 | E198: ARIEL DETERGENTE POLVO COL 400GX24UN | F198: 24 | G198: =Q198 -> 0 | H198: =G198*F198 -> 0 | K198: =R198 -> 0 | M198: =S198 -> 0 | P198: =H198-J198-I198-K198-L198-M198-INVENTARIO!$N198-O198 -> 0 | Q198: =IFERROR(VLOOKUP(D198,'TABL COMPR'!$A:$D,4,0),0) -> 0 | R198: =IFERROR(VLOOKUP(D198,#REF!,4,0),0) -> 0 | S198: =IFERROR(VLOOKUP(D198,#REF!,4,0),0) -> 0 | T198: =IFERROR(VLOOKUP(D198,#REF!,4,0),0) -> 0
A199: =VLOOKUP(INVENTARIO!$D199,LISTA!$A:$E,3,0) -> P&G-FQ | B199: =VLOOKUP(INVENTARIO!$D199,LISTA!$A:$E,4,0) -> CUIDADO DE LA ROPA | C199: =VLOOKUP(INVENTARIO!$D199,LISTA!$A:$E,5,0) -> Ace | D199: 80826043 | E199: ACE DETERGENTE POLVO COL 400GX24UN | F199: 24 | G199: =Q199 -> 0 | H199: =G199*F199 -> 0 | K199: =R199 -> 0 | M199: =S199 -> 0 | P199: =H199-J199-I199-K199-L199-M199-INVENTARIO!$N199-O199 -> 0 | Q199: =IFERROR(VLOOKUP(D199,'TABL COMPR'!$A:$D,4,0),0) -> 0 | R199: =IFERROR(VLOOKUP(D199,#REF!,4,0),0) -> 0 | S199: =IFERROR(VLOOKUP(D199,#REF!,4,0),0) -> 0 | T199: =IFERROR(VLOOKUP(D199,#REF!,4,0),0) -> 0
A200: =VLOOKUP(INVENTARIO!$D200,LISTA!$A:$E,3,0) -> P&G-FQ | B200: =VLOOKUP(INVENTARIO!$D200,LISTA!$A:$E,4,0) -> CUIDADO DEL CABELLO | C200: =VLOOKUP(INVENTARIO!$D200,LISTA!$A:$E,5,0) -> H&S | D200: 80724232 | E200: HS SHAMPOO 2en1 SUAVE Y MANEJ 375CCX12UN | F200: 12 | G200: =Q200 -> 0 | H200: =G200*F200 -> 0 | K200: =R200 -> 0 | M200: =S200 -> 0 | P200: =H200-J200-I200-K200-L200-M200-INVENTARIO!$N200-O200 -> 0 | Q200: =IFERROR(VLOOKUP(D200,'TABL COMPR'!$A:$D,4,0),0) -> 0 | R200: =IFERROR(VLOOKUP(D200,#REF!,4,0),0) -> 0 | S200: =IFERROR(VLOOKUP(D200,#REF!,4,0),0) -> 0 | T200: =IFERROR(VLOOKUP(D200,#REF!,4,0),0) -> 0
A201: =VLOOKUP(INVENTARIO!$D201,LISTA!$A:$E,3,0) -> P&G-FQ | B201: =VLOOKUP(INVENTARIO!$D201,LISTA!$A:$E,4,0) -> CUIDADOPERSONAL | C201: =VLOOKUP(INVENTARIO!$D201,LISTA!$A:$E,5,0) -> Gillette | D201: 80692238 | E201: GILLETTE CLEARGEL COOLWAVE 45GX12UN | F201: 12 | G201: =Q201 -> 0 | H201: =G201*F201 -> 0 | K201: =R201 -> 0 | M201: =S201 -> 0 | P201: =H201-J201-I201-K201-L201-M201-INVENTARIO!$N201-O201 -> 0 | Q201: =IFERROR(VLOOKUP(D201,'TABL COMPR'!$A:$D,4,0),0) -> 0 | R201: =IFERROR(VLOOKUP(D201,#REF!,4,0),0) -> 0 | S201: =IFERROR(VLOOKUP(D201,#REF!,4,0),0) -> 0 | T201: =IFERROR(VLOOKUP(D201,#REF!,4,0),0) -> 0
A202: =VLOOKUP(INVENTARIO!$D202,LISTA!$A:$E,3,0) -> P&G-FQ | B202: =VLOOKUP(INVENTARIO!$D202,LISTA!$A:$E,4,0) -> CUIDADO DEL CABELLO | C202: =VLOOKUP(INVENTARIO!$D202,LISTA!$A:$E,5,0) -> H&S | D202: 80680615 | E202: HS SHAMPOO 2en1 LIMP RENOV 375CCX12UN | F202: 12 | G202: =Q202 -> 0 | H202: =G202*F202 -> 0 | K202: =R202 -> 0 | M202: =S202 -> 0 | P202: =H202-J202-I202-K202-L202-M202-INVENTARIO!$N202-O202 -> 0 | Q202: =IFERROR(VLOOKUP(D202,'TABL COMPR'!$A:$D,4,0),0) -> 0 | R202: =IFERROR(VLOOKUP(D202,#REF!,4,0),0) -> 0 | S202: =IFERROR(VLOOKUP(D202,#REF!,4,0),0) -> 0 | T202: =IFERROR(VLOOKUP(D202,#REF!,4,0),0) -> 0
A203: =VLOOKUP(INVENTARIO!$D203,LISTA!$A:$E,3,0) -> P&G-FQ | B203: =VLOOKUP(INVENTARIO!$D203,LISTA!$A:$E,4,0) -> CUIDADO DEL CABELLO | C203: =VLOOKUP(INVENTARIO!$D203,LISTA!$A:$E,5,0) -> H&S | D203: 80755366 | E203: HS SHAMPOO ANTI COMEZON 180CCX12UN | F203: 12 | G203: =Q203 -> 0 | H203: =G203*F203 -> 0 | K203: =R203 -> 0 | M203: =S203 -> 0 | P203: =H203-J203-I203-K203-L203-M203-INVENTARIO!$N203-O203 -> 0 | Q203: =IFERROR(VLOOKUP(D203,'TABL COMPR'!$A:$D,4,0),0) -> 0 | R203: =IFERROR(VLOOKUP(D203,#REF!,4,0),0) -> 0 | S203: =IFERROR(VLOOKUP(D203,#REF!,4,0),0) -> 0 | T203: =IFERROR(VLOOKUP(D203,#REF!,4,0),0) -> 0
A204: =VLOOKUP(INVENTARIO!$D204,LISTA!$A:$E,3,0) -> P&G-FQ | B204: =VLOOKUP(INVENTARIO!$D204,LISTA!$A:$E,4,0) -> CUIDADO FEMENINO | C204: =VLOOKUP(INVENTARIO!$D204,LISTA!$A:$E,5,0) -> Always | D204: 80684304 | E204: ALWAYS TOALLAS SEDASEC F ABUND 60GX24UN | F204: 24 | G204: =Q204 -> 0 | H204: =G204*F204 -> 0 | K204: =R204 -> 0 | M204: =S204 -> 0 | P204: =H204-J204-I204-K204-L204-M204-INVENTARIO!$N204-O204 -> 0 | Q204: =IFERROR(VLOOKUP(D204,'TABL COMPR'!$A:$D,4,0),0) -> 0 | R204: =IFERROR(VLOOKUP(D204,#REF!,4,0),0) -> 0 | S204: =IFERROR(VLOOKUP(D204,#REF!,4,0),0) -> 0 | T204: =IFERROR(VLOOKUP(D204,#REF!,4,0),0) -> 0
... A242: =VLOOKUP(INVENTARIO!$D242,LISTA!$A:$E,3,0) -> P&G-FQ | B242: =VLOOKUP(INVENTARIO!$D242,LISTA!$A:$E,4,0) -> CUIDADO DEL CABELLO | C242: =VLOOKUP(INVENTARIO!$D242,LISTA!$A:$E,5,0) -> Pantene | D242: 80687013 | E242: PTN ACOND COLAGENO 250CCX12UN | F242: 12 | G242: =Q242 -> 0 | H242: =G242*F242 -> 0 | K242: =R242 -> 0 | M242: =S242 -> 0 | P242: =H242-J242-I242-K242-L242-M242-INVENTARIO!$N242-O242 -> 0 | Q242: =IFERROR(VLOOKUP(D242,'TABL COMPR'!$A:$D,4,0),0) -> 0 | R242: =IFERROR(VLOOKUP(D242,#REF!,4,0),0) -> 0 | S242: =IFERROR(VLOOKUP(D242,#REF!,4,0),0) -> 0 | T242: =IFERROR(VLOOKUP(D242,#REF!,4,0),0) -> 0
A243: =VLOOKUP(INVENTARIO!$D243,LISTA!$A:$E,3,0) -> P&G-FQ | B243: =VLOOKUP(INVENTARIO!$D243,LISTA!$A:$E,4,0) -> AFEITADO | C243: =VLOOKUP(INVENTARIO!$D243,LISTA!$A:$E,5,0) -> Gillette UG | D243: 80685930 | E243: GILLETTE BLIST PB3X2 SENSECARE 23GX72UN | F243: 72 | G243: =Q243 -> 0 | H243: =INVENTARIO!$G243 -> 0 | K243: =R243 -> 0 | M243: =S243 -> 0 | P243: =H243-J243-I243-K243-L243-M243-INVENTARIO!$N243-O243 -> 0 | Q243: =IFERROR(VLOOKUP(D243,'TABL COMPR'!$A:$D,4,0),0) -> 0 | R243: =IFERROR(VLOOKUP(D243,#REF!,4,0),0) -> 0 | S243: =IFERROR(VLOOKUP(D243,#REF!,4,0),0) -> 0 | T243: =IFERROR(VLOOKUP(D243,#REF!,4,0),0) -> 0
A244: =VLOOKUP(INVENTARIO!$D244,LISTA!$A:$E,3,0) -> P&G-FQ | B244: =VLOOKUP(INVENTARIO!$D244,LISTA!$A:$E,4,0) -> AFEITADO | C244: =VLOOKUP(INVENTARIO!$D244,LISTA!$A:$E,5,0) -> Gillette UG | D244: 80685905 | E244: GILLETTE BLISTER PB3X4UN MASC 46GX36UN | F244: 36 | G244: =Q244 -> 0 | H244: =INVENTARIO!$G244 -> 0 | K244: =R244 -> 0 | M244: =S244 -> 0 | P244: =H244-J244-I244-K244-L244-M244-INVENTARIO!$N244-O244 -> 0 | Q244: =IFERROR(VLOOKUP(D244,'TABL COMPR'!$A:$D,4,0),0) -> 0 | R244: =IFERROR(VLOOKUP(D244,#REF!,4,0),0) -> 0 | S244: =IFERROR(VLOOKUP(D244,#REF!,4,0),0) -> 0 | T244: =IFERROR(VLOOKUP(D244,#REF!,4,0),0) -> 0
A245: =VLOOKUP(INVENTARIO!$D245,LISTA!$A:$E,3,0) -> P&G-FQ | B245: =VLOOKUP(INVENTARIO!$D245,LISTA!$A:$E,4,0) -> AFEITADO | C245: =VLOOKUP(INVENTARIO!$D245,LISTA!$A:$E,5,0) -> Gillette UG | D245: 80685855 | E245: GILLETTE RISTRA PB3X10UN MASC 120GX12RIS | F245: 12 | G245: =Q245 -> 0 | H245: =G245*F245 -> 0 | K245: =R245 -> 0 | M245: =S245 -> 0 | P245: =H245-J245-I245-K245-L245-M245-INVENTARIO!$N245-O245 -> 0 | Q245: =IFERROR(VLOOKUP(D245,'TABL COMPR'!$A:$D,4,0),0) -> 0 | R245: =IFERROR(VLOOKUP(D245,#REF!,4,0),0) -> 0 | S245: =IFERROR(VLOOKUP(D245,#REF!,4,0),0) -> 0 | T245: =IFERROR(VLOOKUP(D245,#REF!,4,0),0) -> 0
A246: =VLOOKUP(INVENTARIO!$D246,LISTA!$A:$E,3,0) -> P&G-FQ | B246: =VLOOKUP(INVENTARIO!$D246,LISTA!$A:$E,4,0) -> CUIDADO FEMENINO | C246: =VLOOKUP(INVENTARIO!$D246,LISTA!$A:$E,5,0) -> Always | D246: 80684784 | E246: ALWAYS PROTE DIAR LARGOS 50UND 146GX24UN | F246: 24 | G246: =Q246 -> 0 | H246: =G246*F246 -> 0 | K246: =R246 -> 0 | M246: =S246 -> 0 | P246: =H246-J246-I246-K246-L246-M246-INVENTARIO!$N246-O246 -> 0 | Q246: =IFERROR(VLOOKUP(D246,'TABL COMPR'!$A:$D,4,0),0) -> 0 | R246: =IFERROR(VLOOKUP(D246,#REF!,4,0),0) -> 0 | S246: =IFERROR(VLOOKUP(D246,#REF!,4,0),0) -> 0 | T246: =IFERROR(VLOOKUP(D246,#REF!,4,0),0) -> 0
A247: =VLOOKUP(INVENTARIO!$D247,LISTA!$A:$E,3,0) -> P&G-FQ | B247: =VLOOKUP(INVENTARIO!$D247,LISTA!$A:$E,4,0) -> CUIDADOPERSONAL | C247: =VLOOKUP(INVENTARIO!$D247,LISTA!$A:$E,5,0) -> Gillette | D247: 80692231 | E247: GILLETTE CLEARGEL COOLWAVE 82GRX 12UND | F247: 12 | G247: =Q247 -> 0 | H247: =G247*F247 -> 0 | K247: =R247 -> 0 | M247: =S247 -> 0 | P247: =H247-J247-I247-K247-L247-M247-INVENTARIO!$N247-O247 -> 0 | Q247: =IFERROR(VLOOKUP(D247,'TABL COMPR'!$A:$D,4,0),0) -> 0 | R247: =IFERROR(VLOOKUP(D247,#REF!,4,0),0) -> 0 | S247: =IFERROR(VLOOKUP(D247,#REF!,4,0),0) -> 0 | T247: =IFERROR(VLOOKUP(D247,#REF!,4,0),0) -> 0
A248: =VLOOKUP(INVENTARIO!$D248,LISTA!$A:$E,3,0) -> P&G-FQ | B248: =VLOOKUP(INVENTARIO!$D248,LISTA!$A:$E,4,0) -> CUIDADO FEMENINO | C248: =VLOOKUP(INVENTARIO!$D248,LISTA!$A:$E,5,0) -> Always | D248: 80684299 | E248: ALWAYS TOALL NOCT SEDA F ABUND 101GX12UN | F248: 12 | G248: =Q248 -> 0 | H248: =G248*F248 -> 0 | K248: =R248 -> 0 | M248: =S248 -> 0 | P248: =H248-J248-I248-K248-L248-M248-INVENTARIO!$N248-O248 -> 0 | Q248: =IFERROR(VLOOKUP(D248,'TABL COMPR'!$A:$D,4,0),0) -> 0 | R248: =IFERROR(VLOOKUP(D248,#REF!,4,0),0) -> 0 | S248: =IFERROR(VLOOKUP(D248,#REF!,4,0),0) -> 0 | T248: =IFERROR(VLOOKUP(D248,#REF!,4,0),0) -> 0
A249: =VLOOKUP(INVENTARIO!$D249,LISTA!$A:$E,3,0) -> P&G-FQ | B249: =VLOOKUP(INVENTARIO!$D249,LISTA!$A:$E,4,0) -> AFEITADO | C249: =VLOOKUP(INVENTARIO!$D249,LISTA!$A:$E,5,0) -> Gillette UG | D249: 80682872 | E249: GILLETTE RIST HOJILL SUPERTHIN 60GX24RIS | F249: 24 | G249: =Q249 -> 0 | H249: =G249*F249 -> 0 | K249: =R249 -> 0 | M249: =S249 -> 0 | P249: =H249-J249-I249-K249-L249-M249-INVENTARIO!$N249-O249 -> 0 | Q249: =IFERROR(VLOOKUP(D249,'TABL COMPR'!$A:$D,4,0),0) -> 0 | R249: =IFERROR(VLOOKUP(D249,#REF!,4,0),0) -> 0 | S249: =IFERROR(VLOOKUP(D249,#REF!,4,0),0) -> 0 | T249: =IFERROR(VLOOKUP(D249,#REF!,4,0),0) -> 0
A250: =VLOOKUP(INVENTARIO!$D250,LISTA!$A:$E,3,0) -> P&G-FQ | B250: =VLOOKUP(INVENTARIO!$D250,LISTA!$A:$E,4,0) -> CUIDADO DE LA ROPA | C250: =VLOOKUP(INVENTARIO!$D250,LISTA!$A:$E,5,0) -> Ariel | D250: 80682213 | E250: ARIEL DET LIQ REG 1800CCX6UN | F250: 6 | G250: =Q250 -> 0 | H250: =G250*F250 -> 0 | K250: =R250 -> 0 | M250: =S250 -> 0 | P250: =H250-J250-I250-K250-L250-M250-INVENTARIO!$N250-O250 -> 0 | Q250: =IFERROR(VLOOKUP(D250,'TABL COMPR'!$A:$D,4,0),0) -> 0 | R250: =IFERROR(VLOOKUP(D250,#REF!,4,0),0) -> 0 | S250: =IFERROR(VLOOKUP(D250,#REF!,4,0),0) -> 0 | T250: =IFERROR(VLOOKUP(D250,#REF!,4,0),0) -> 0
A251: =VLOOKUP(INVENTARIO!$D251,LISTA!$A:$E,3,0) -> P&G-FQ | B251: =VLOOKUP(INVENTARIO!$D251,LISTA!$A:$E,4,0) -> CUIDADO DEL CABELLO | C251: =VLOOKUP(INVENTARIO!$D251,LISTA!$A:$E,5,0) -> H&S | D251: 80680718 | E251: HS SHAMPOO C/OLD SPICE 375MLX12UN | F251: 12 | G251: =Q251 -> 0 | H251: =G251*F251 -> 0 | K251: =R251 -> 0 | M251: =S251 -> 0 | P251: =H251-J251-I251-K251-L251-M251-INVENTARIO!$N251-O251 -> 0 | Q251: =IFERROR(VLOOKUP(D251,'TABL COMPR'!$A:$D,4,0),0) -> 0 | R251: =IFERROR(VLOOKUP(D251,#REF!,4,0),0) -> 0 | S251: =IFERROR(VLOOKUP(D251,#REF!,4,0),0) -> 0 | T251: =IFERROR(VLOOKUP(D251,#REF!,4,0),0) -> 0
A252: =VLOOKUP(INVENTARIO!$D252,LISTA!$A:$E,3,0) -> P&G-FQ | B252: =VLOOKUP(INVENTARIO!$D252,LISTA!$A:$E,4,0) -> CUIDADO DEL CABELLO | C252: =VLOOKUP(INVENTARIO!$D252,LISTA!$A:$E,5,0) -> H&S | D252: 80680717 | E252: HS SHAMPOO LIMP RENOV 375CCX12UN | F252: 12 | G252: =Q252 -> 0 | H252: =G252*F252 -> 0 | K252: =R252 -> 0 | M252: =S252 -> 0 | P252: =H252-J252-I252-K252-L252-M252-INVENTARIO!$N252-O252 -> 0 | Q252: =IFERROR(VLOOKUP(D252,'TABL COMPR'!$A:$D,4,0),0) -> 0 | R252: =IFERROR(VLOOKUP(D252,#REF!,4,0),0) -> 0 | S252: =IFERROR(VLOOKUP(D252,#REF!,4,0),0) -> 0 | T252: =IFERROR(VLOOKUP(D252,#REF!,4,0),0) -> 0
A253: =VLOOKUP(INVENTARIO!$D253,LISTA!$A:$E,3,0) -> P&G-FQ | B253: =VLOOKUP(INVENTARIO!$D253,LISTA!$A:$E,4,0) -> CUIDADO DEL CABELLO | C253: =VLOOKUP(INVENTARIO!$D253,LISTA!$A:$E,5,0) -> H&S | D253: 80755365 | E253: HS SHAMPOO ANTI COMEZON 375CCX12UN | F253: 12 | G253: =Q253 -> 0 | H253: =G253*F253 -> 0 | K253: =R253 -> 0 | M253: =S253 -> 0 | P253: =H253-J253-I253-K253-L253-M253-INVENTARIO!$N253-O253 -> 0 | Q253: =IFERROR(VLOOKUP(D253,'TABL COMPR'!$A:$D,4,0),0) -> 0 | R253: =IFERROR(VLOOKUP(D253,#REF!,4,0),0) -> 0 | S253: =IFERROR(VLOOKUP(D253,#REF!,4,0),0) -> 0 | T253: =IFERROR(VLOOKUP(D253,#REF!,4,0),0) -> 0
A254: =VLOOKUP(INVENTARIO!$D254,LISTA!$A:$E,3,0) -> P&G-FQ | B254: =VLOOKUP(INVENTARIO!$D254,LISTA!$A:$E,4,0) -> CUIDADO DEL CABELLO | C254: =VLOOKUP(INVENTARIO!$D254,LISTA!$A:$E,5,0) -> H&S | D254: 80724230 | E254: HS SHAMPOO 2en1 SUAVE Y MANEJ 180CCX12UN | F254: 12 | G254: =Q254 -> 0 | H254: =G254*F254 -> 0 | K254: =R254 -> 0 | M254: =S254 -> 0 | P254: =H254-J254-I254-K254-L254-M254-INVENTARIO!$N254-O254 -> 0 | Q254: =IFERROR(VLOOKUP(D254,'TABL COMPR'!$A:$D,4,0),0) -> 0 | R254: =IFERROR(VLOOKUP(D254,#REF!,4,0),0) -> 0 | S254: =IFERROR(VLOOKUP(D254,#REF!,4,0),0) -> 0 | T254: =IFERROR(VLOOKUP(D254,#REF!,4,0),0) -> 0
A255: =VLOOKUP(INVENTARIO!$D255,LISTA!$A:$E,3,0) -> P&G-FQ | B255: =VLOOKUP(INVENTARIO!$D255,LISTA!$A:$E,4,0) -> CUIDADO DEL CABELLO | C255: =VLOOKUP(INVENTARIO!$D255,LISTA!$A:$E,5,0) -> H&S | D255: 80680655 | E255: HS SHAMPOO ANTIFALL 375CCX12UN | F255: 12 | G255: =Q255 -> 0 | H255: =G255*F255 -> 0 | K255: =R255 -> 0 | M255: =S255 -> 0 | P255: =H255-J255-I255-K255-L255-M255-INVENTARIO!$N255-O255 -> 0 | Q255: =IFERROR(VLOOKUP(D255,'TABL COMPR'!$A:$D,4,0),0) -> 0 | R255: =IFERROR(VLOOKUP(D255,#REF!,4,0),0) -> 0 | S255: =IFERROR(VLOOKUP(D255,#REF!,4,0),0) -> 0 | T255: =IFERROR(VLOOKUP(D255,#REF!,4,0),0) -> 0
A256: =VLOOKUP(INVENTARIO!$D256,LISTA!$A:$E,3,0) -> P&G-FQ | B256: =VLOOKUP(INVENTARIO!$D256,LISTA!$A:$E,4,0) -> CUIDADO DEL CABELLO | C256: =VLOOKUP(INVENTARIO!$D256,LISTA!$A:$E,5,0) -> H&S | D256: 80680716 | E256: HS SHAMPOO LIMP RENOV 180CCX12UN | F256: 12 | G256: =Q256 -> 0 | H256: =G256*F256 -> 0 | K256: =R256 -> 0 | M256: =S256 -> 0 | P256: =H256-J256-I256-K256-L256-M256-INVENTARIO!$N256-O256 -> 0 | Q256: =IFERROR(VLOOKUP(D256,'TABL COMPR'!$A:$D,4,0),0) -> 0 | R256: =IFERROR(VLOOKUP(D256,#REF!,4,0),0) -> 0 | S256: =IFERROR(VLOOKUP(D256,#REF!,4,0),0) -> 0 | T256: =IFERROR(VLOOKUP(D256,#REF!,4,0),0) -> 0
... A275: =VLOOKUP(INVENTARIO!$D275,LISTA!$A:$E,3,0) -> P&G-FQ | B275: =VLOOKUP(INVENTARIO!$D275,LISTA!$A:$E,4,0) -> Cuidado Bucal | C275: =VLOOKUP(INVENTARIO!$D275,LISTA!$A:$E,5,0) -> Oral B | D275: 80353741 | E275: ORALB CEP 1-2-3 PAQX6UN 120GX6RIS | F275: 6 | G275: =Q275 -> 0 | H275: =G275*F275 -> 0 | K275: =R275 -> 0 | M275: =S275 -> 0 | P275: =H275-J275-I275-K275-L275-M275-INVENTARIO!$N275-O275 -> 0 | Q275: =IFERROR(VLOOKUP(D275,'TABL COMPR'!$A:$D,4,0),0) -> 0 | R275: =IFERROR(VLOOKUP(D275,#REF!,4,0),0) -> 0 | S275: =IFERROR(VLOOKUP(D275,#REF!,4,0),0) -> 0 | T275: =IFERROR(VLOOKUP(D275,#REF!,4,0),0) -> 0
A276: =VLOOKUP(INVENTARIO!$D276,LISTA!$A:$E,3,0) -> P&G-FQ | B276: =VLOOKUP(INVENTARIO!$D276,LISTA!$A:$E,4,0) -> AFEITADO | C276: =VLOOKUP(INVENTARIO!$D276,LISTA!$A:$E,5,0) -> Venus | D276: 80351964 | E276: VENUS BLISTER SIMPLYX2UN FEM 26GX12UN | F276: 12 | G276: =Q276 -> 0 | H276: =INVENTARIO!$F276*INVENTARIO!$G276 -> 0 | K276: =R276 -> 0 | M276: =S276 -> 0 | P276: =H276-J276-I276-K276-L276-M276-INVENTARIO!$N276-O276 -> 0 | Q276: =IFERROR(VLOOKUP(D276,'TABL COMPR'!$A:$D,4,0),0) -> 0 | R276: =IFERROR(VLOOKUP(D276,#REF!,4,0),0) -> 0 | S276: =IFERROR(VLOOKUP(D276,#REF!,4,0),0) -> 0 | T276: =IFERROR(VLOOKUP(D276,#REF!,4,0),0) -> 0
A277: =VLOOKUP(INVENTARIO!$D277,LISTA!$A:$E,3,0) -> P&G-FQ | B277: =VLOOKUP(INVENTARIO!$D277,LISTA!$A:$E,4,0) -> AFEITADO | C277: =VLOOKUP(INVENTARIO!$D277,LISTA!$A:$E,5,0) -> Venus | D277: 80351962 | E277: VENUS BLISTER SIMPLYX4UN FEM 52GX6UN | F277: 6 | G277: =Q277 -> 0 | H277: =INVENTARIO!$G277 -> 0 | K277: =R277 -> 0 | M277: =S277 -> 0 | P277: =H277-J277-I277-K277-L277-M277-INVENTARIO!$N277-O277 -> 0 | Q277: =IFERROR(VLOOKUP(D277,'TABL COMPR'!$A:$D,4,0),0) -> 0 | R277: =IFERROR(VLOOKUP(D277,#REF!,4,0),0) -> 0 | S277: =IFERROR(VLOOKUP(D277,#REF!,4,0),0) -> 0 | T277: =IFERROR(VLOOKUP(D277,#REF!,4,0),0) -> 0
A278: =VLOOKUP(INVENTARIO!$D278,LISTA!$A:$E,3,0) -> P&G-FQ | B278: =VLOOKUP(INVENTARIO!$D278,LISTA!$A:$E,4,0) -> AFEITADO | C278: =VLOOKUP(INVENTARIO!$D278,LISTA!$A:$E,5,0) -> Venus | D278: 80351959 | E278: VENUS RISTRA SIMPLYX8UN FEM 104GX10RIS | F278: 10 | G278: =Q278 -> 0 | H278: =G278*F278 -> 0 | K278: =R278 -> 0 | M278: =S278 -> 0 | P278: =H278-J278-I278-K278-L278-M278-INVENTARIO!$N278-O278 -> 0 | Q278: =IFERROR(VLOOKUP(D278,'TABL COMPR'!$A:$D,4,0),0) -> 0 | R278: =IFERROR(VLOOKUP(D278,#REF!,4,0),0) -> 0 | S278: =IFERROR(VLOOKUP(D278,#REF!,4,0),0) -> 0 | T278: =IFERROR(VLOOKUP(D278,#REF!,4,0),0) -> 0
A279: =VLOOKUP(INVENTARIO!$D279,LISTA!$A:$E,3,0) -> P&G-FQ | B279: =VLOOKUP(INVENTARIO!$D279,LISTA!$A:$E,4,0) -> CUIDADO FEMENINO | C279: =VLOOKUP(INVENTARIO!$D279,LISTA!$A:$E,5,0) -> TAMPAX | D279: 80350783 | E279: TAMPAX PEARL SUPER 18UND 108GX12UN | F279: 12 | G279: =Q279 -> 0 | H279: =G279*F279 -> 0 | K279: =R279 -> 0 | M279: =S279 -> 0 | P279: =H279-J279-I279-K279-L279-M279-INVENTARIO!$N279-O279 -> 0 | Q279: =IFERROR(VLOOKUP(D279,'TABL COMPR'!$A:$D,4,0),0) -> 0 | R279: =IFERROR(VLOOKUP(D279,#REF!,4,0),0) -> 0 | S279: =IFERROR(VLOOKUP(D279,#REF!,4,0),0) -> 0 | T279: =IFERROR(VLOOKUP(D279,#REF!,4,0),0) -> 0
A280: =VLOOKUP(INVENTARIO!$D280,LISTA!$A:$E,3,0) -> P&G-FQ | B280: =VLOOKUP(INVENTARIO!$D280,LISTA!$A:$E,4,0) -> CUIDADO DEL CABELLO | C280: =VLOOKUP(INVENTARIO!$D280,LISTA!$A:$E,5,0) -> H&S | D280: 80350319 | E280: HS ACOND ANTIFALL 300CCX12UN | F280: 12 | G280: =Q280 -> 0 | H280: =G280*F280 -> 0 | K280: =R280 -> 0 | M280: =S280 -> 0 | P280: =H280-J280-I280-K280-L280-M280-INVENTARIO!$N280-O280 -> 0 | Q280: =IFERROR(VLOOKUP(D280,'TABL COMPR'!$A:$D,4,0),0) -> 0 | R280: =IFERROR(VLOOKUP(D280,#REF!,4,0),0) -> 0 | S280: =IFERROR(VLOOKUP(D280,#REF!,4,0),0) -> 0 | T280: =IFERROR(VLOOKUP(D280,#REF!,4,0),0) -> 0
A281: =VLOOKUP(INVENTARIO!$D281,LISTA!$A:$E,3,0) -> P&G-FQ | B281: =VLOOKUP(INVENTARIO!$D281,LISTA!$A:$E,4,0) -> CUIDADO DEL BEBE | C281: =VLOOKUP(INVENTARIO!$D281,LISTA!$A:$E,5,0) -> Pampers | D281: 80348037 | E281: PAMPERS PAÑALES CONFORT SEC G 463GX8UN | F281: 8 | G281: =Q281 -> 0 | H281: =G281*F281 -> 0 | K281: =R281 -> 0 | M281: =S281 -> 0 | P281: =H281-J281-I281-K281-L281-M281-INVENTARIO!$N281-O281 -> 0 | Q281: =IFERROR(VLOOKUP(D281,'TABL COMPR'!$A:$D,4,0),0) -> 0 | R281: =IFERROR(VLOOKUP(D281,#REF!,4,0),0) -> 0 | S281: =IFERROR(VLOOKUP(D281,#REF!,4,0),0) -> 0 | T281: =IFERROR(VLOOKUP(D281,#REF!,4,0),0) -> 0
A282: =VLOOKUP(INVENTARIO!$D282,LISTA!$A:$E,3,0) -> P&G-FQ | B282: =VLOOKUP(INVENTARIO!$D282,LISTA!$A:$E,4,0) -> CUIDADO DEL BEBE | C282: =VLOOKUP(INVENTARIO!$D282,LISTA!$A:$E,5,0) -> Pampers | D282: 80348010 | E282: PAMPERS PAÑALES CONFORT SEC XG 451GX8UN | F282: 8 | G282: =Q282 -> 0 | H282: =G282*F282 -> 0 | K282: =R282 -> 0 | M282: =S282 -> 0 | P282: =H282-J282-I282-K282-L282-M282-INVENTARIO!$N282-O282 -> 0 | Q282: =IFERROR(VLOOKUP(D282,'TABL COMPR'!$A:$D,4,0),0) -> 0 | R282: =IFERROR(VLOOKUP(D282,#REF!,4,0),0) -> 0 | S282: =IFERROR(VLOOKUP(D282,#REF!,4,0),0) -> 0 | T282: =IFERROR(VLOOKUP(D282,#REF!,4,0),0) -> 0
A283: =VLOOKUP(INVENTARIO!$D283,LISTA!$A:$E,3,0) -> P&G-FQ | B283: =VLOOKUP(INVENTARIO!$D283,LISTA!$A:$E,4,0) -> CUIDADO DEL BEBE | C283: =VLOOKUP(INVENTARIO!$D283,LISTA!$A:$E,5,0) -> Pampers | D283: 80347948 | E283: PAMPERS PAÑALES CONFORT SEC XXG 432GX8UN | F283: 8 | G283: =Q283 -> 0 | H283: =G283*F283 -> 0 | K283: =R283 -> 0 | M283: =S283 -> 0 | P283: =H283-J283-I283-K283-L283-M283-INVENTARIO!$N283-O283 -> 0 | Q283: =IFERROR(VLOOKUP(D283,'TABL COMPR'!$A:$D,4,0),0) -> 0 | R283: =IFERROR(VLOOKUP(D283,#REF!,4,0),0) -> 0 | S283: =IFERROR(VLOOKUP(D283,#REF!,4,0),0) -> 0 | T283: =IFERROR(VLOOKUP(D283,#REF!,4,0),0) -> 0
A284: =VLOOKUP(INVENTARIO!$D284,LISTA!$A:$E,3,0) -> P&G-FQ | B284: =VLOOKUP(INVENTARIO!$D284,LISTA!$A:$E,4,0) -> CUIDADO DEL CABELLO | C284: =VLOOKUP(INVENTARIO!$D284,LISTA!$A:$E,5,0) -> Pantene | D284: 80342866 | E284: PTN ACOND BAMBU 200CCX12UN | F284: 12 | G284: =Q284 -> 0 | H284: =G284*F284 -> 0 | K284: =R284 -> 0 | M284: =S284 -> 0 | P284: =H284-J284-I284-K284-L284-M284-INVENTARIO!$N284-O284 -> 0 | Q284: =IFERROR(VLOOKUP(D284,'TABL COMPR'!$A:$D,4,0),0) -> 0 | R284: =IFERROR(VLOOKUP(D284,#REF!,4,0),0) -> 0 | S284: =IFERROR(VLOOKUP(D284,#REF!,4,0),0) -> 0 | T284: =IFERROR(VLOOKUP(D284,#REF!,4,0),0) -> 0
A285: =VLOOKUP(INVENTARIO!$D285,LISTA!$A:$E,3,0) -> P&G-FQ | B285: =VLOOKUP(INVENTARIO!$D285,LISTA!$A:$E,4,0) -> CUIDADO DEL CABELLO | C285: =VLOOKUP(INVENTARIO!$D285,LISTA!$A:$E,5,0) -> Pantene | D285: 80342865 | E285: PTN ACOND BAMBU 400CCX12UN | F285: 12 | G285: =Q285 -> 0 | H285: =G285*F285 -> 0 | K285: =R285 -> 0 | M285: =S285 -> 0 | P285: =H285-J285-I285-K285-L285-M285-INVENTARIO!$N285-O285 -> 0 | Q285: =IFERROR(VLOOKUP(D285,'TABL COMPR'!$A:$D,4,0),0) -> 0 | R285: =IFERROR(VLOOKUP(D285,#REF!,4,0),0) -> 0 | S285: =IFERROR(VLOOKUP(D285,#REF!,4,0),0) -> 0 | T285: =IFERROR(VLOOKUP(D285,#REF!,4,0),0) -> 0
A286: =VLOOKUP(INVENTARIO!$D286,LISTA!$A:$E,3,0) -> P&G-FQ | B286: =VLOOKUP(INVENTARIO!$D286,LISTA!$A:$E,4,0) -> CUIDADO DEL CABELLO | C286: =VLOOKUP(INVENTARIO!$D286,LISTA!$A:$E,5,0) -> Pantene | D286: 80342857 | E286: PTN SHAMPOO BAMBU 400CCX12UN | F286: 12 | G286: =Q286 -> 0 | H286: =G286*F286 -> 0 | K286: =R286 -> 0 | M286: =S286 -> 0 | P286: =H286-J286-I286-K286-L286-M286-INVENTARIO!$N286-O286 -> 0 | Q286: =IFERROR(VLOOKUP(D286,'TABL COMPR'!$A:$D,4,0),0) -> 0 | R286: =IFERROR(VLOOKUP(D286,#REF!,4,0),0) -> 0 | S286: =IFERROR(VLOOKUP(D286,#REF!,4,0),0) -> 0 | T286: =IFERROR(VLOOKUP(D286,#REF!,4,0),0) -> 0
...

Sheet TABL COMPR
A3: CodProducto | B3: DescrProducto | C3: UnidadCompra | D3: Suma de Cantidad
A4: (en blanco) | B4: (en blanco) | C4: (en blanco) | E4: =VLOOKUP(A4,INVENTARIO!$D:$E,1,0) -> #N/A | F4: =A4=E4 -> #N/A
A5: Total general | E5: =VLOOKUP(A5,INVENTARIO!$D:$E,1,0) -> #N/A | F5: =A5=E5 -> #N/A
E6: =VLOOKUP(A6,INVENTARIO!$D:$E,1,0) -> #N/A | F6: =A6=E6 -> #N/A
E7: =VLOOKUP(A7,INVENTARIO!$D:$E,1,0) -> #N/A | F7: =A7=E7 -> #N/A
E8: =VLOOKUP(A8,INVENTARIO!$D:$E,1,0) -> #N/A | F8: =A8=E8 -> #N/A
E9: =VLOOKUP(A9,INVENTARIO!$D:$E,1,0) -> #N/A | F9: =A9=E9 -> #N/A
E10: =VLOOKUP(A10,INVENTARIO!$D:$E,1,0) -> #N/A | F10: =A10=E10 -> #N/A
E11: =VLOOKUP(A11,INVENTARIO!$D:$E,1,0) -> #N/A | F11: =A11=E11 -> #N/A
E12: =VLOOKUP(A12,INVENTARIO!$D:$E,1,0) -> #N/A | F12: =A12=E12 -> #N/A
E13: =VLOOKUP(A13,INVENTARIO!$D:$E,1,0) -> #N/A | F13: =A13=E13 -> #N/A
E14: =VLOOKUP(A14,INVENTARIO!$D:$E,1,0) -> #N/A | F14: =A14=E14 -> #N/A
E15: =VLOOKUP(A15,INVENTARIO!$D:$E,1,0) -> #N/A | F15: =A15=E15 -> #N/A
E16: =VLOOKUP(A16,INVENTARIO!$D:$E,1,0) -> #N/A | F16: =A16=E16 -> #N/A
E17: =VLOOKUP(A17,INVENTARIO!$D:$E,1,0) -> #N/A | F17: =A17=E17 -> #N/A
... E232: =VLOOKUP(A232,INVENTARIO!$D:$E,1,0) -> #N/A | F232: =A232=E232 -> #N/A

Sheet COMPRA 03,07
A1: CódigoCompra | B1: FechaCompra | C1: CodProducto | D1: DescrProducto | E1: CodCategoría | F1: DescrCategoría | G1: CodFamilia | H1: DescrFamilia | I1: CodMarca | J1: DescrMarca | K1: CodTipoInv | L1: DescrTipoInv | M1: CodProdProve | N1: Cantidad | O1: UnidadCompra | P1: PrecioUnitario | Q1: Subtotal | R1: Total con IVA | S1: Descuento | T1: Descuento, % | U1: Peso Neto | V1: Kilos | W1: Peso Bruto | X1: Volumen | Y1: CodTrans | Z1: DescTrans | AA1: CodCausTrans | AB1: DescCausTrans | AC1: CodigoUsuario | AD1: CedulaUsuario | AE1: NombreUsuario | AF1: TelfUsuario | AG1: DireccionUsuario | AH1: GrupoUsuario | AI1: CodigoProveedor | AJ1: RucProveedor | AK1: RazonSocial | AL1: DirecProveedor | AM1: FechaCreacion (Proveedor) | AN1: Tipo de proveedor | AO1: Tipo de proveedor (Nombre) | AP1: Tipo de compra | AQ1: Tipo de compra (Nombre) | AR1: EstaCompra | AS1: Comentario Detalle | AT1: NúmeroCompra | AU1: Comentario Cabecera | AV1: Fecha Ingreso a Sistema

Sheet LISTA
A1: Material | B1: Descripción | C1: NEGOCIO | D1: Categoría | E1: Marca | F1: Empaque | G1: UD por CJ | H1: IVA | I1: Art 18 Lisaea | J1: PC_FQ Und S/IVA | K1: PC_FQ Und C/IVA | L1: PC_FQ Caja S/IVA | M1: PC_FQ Caja C/IVA | N1: PV_FQ Und S/IVA | O1: PV_FQ Und C/IVA | P1: PV_FQ Caja S/IVA | Q1: PV_FQ Caja C/IVA | R1: Precio RDV Und S/IVA | S1: Precio RDV Und C/IVA
A2: FN0601 | B2: POMAR BRUT 0,75LxC12 (N) | C2: CYM-FQ | D2: Espumantes | E2: Pomar | F2: 0,750 KG | G2: 1 | H2: 16% | I2: 0.27 | J2: 12.11 | K2: 14.32 | L2: 12.11 | M2: 14.32 | N2: 13.79 | O2: 16 | P2: 13.79 | Q2: 16 | R2: 16.94 | S2: 20
A3: FN0603 | B3: POMAR BRUT 0,75LxC6 (N) | C3: CYM-FQ | D3: Espumantes | E3: Pomar | F3: 0,000 KG | G3: 1 | H3: 16% | I3: 0.27 | J3: 12.11 | K3: 14.32 | L3: 12.11 | M3: 14.32 | N3: 13.79 | O3: 16 | P3: 13.79 | Q3: 16 | R3: 16.94 | S3: 20
A4: FN0606 | B4: POMAR BRUT 0,75LxC12 EE (N) | C4: CYM-FQ | D4: Espumantes | E4: Pomar | F4: 0,750 KG | G4: 1 | H4: 16% | I4: 0.27 | J4: 43.14 | K4: 50.31 | L4: 43.14 | M4: 50.31 | N4: 48.27 | O4: 55.99 | P4: 48.27 | Q4: 55.99 | R4: 60.04 | S4: 69.99
A5: FN0610 | B5: POMAR BRUT NATURE 0,75LxC12 (N) | C5: CYM-FQ | D5: Espumantes | E5: Pomar | F5: 0,750 KG | G5: 1 | H5: 16% | I5: 0.27 | J5: 13.97 | K5: 16.48 | L5: 13.97 | M5: 16.48 | N5: 15.86 | O5: 18.4 | P5: 15.86 | Q5: 18.4 | R5: 19.53 | S5: 23
A6: FN0612 | B6: POMAR DEMISEC 0,75LxC12 (N) | C6: CYM-FQ | D6: Espumantes | E6: Pomar | F6: 0,750 KG | G6: 1 | H6: 16% | I6: 0.27 | J6: 12.11 | K6: 14.32 | L6: 12.11 | M6: 14.32 | N6: 13.79 | O6: 16 | P6: 13.79 | Q6: 16 | R6: 16.94 | S6: 20
A7: FN0614 | B7: POMAR DEMISEC 0,75LxC6 (N) | C7: CYM-FQ | D7: Espumantes | E7: Pomar | F7: 0,000 KG | G7: 1 | H7: 16% | I7: 0.27 | J7: 12.11 | K7: 14.32 | L7: 12.11 | M7: 14.32 | N7: 13.79 | O7: 16 | P7: 13.79 | Q7: 16 | R7: 16.94 | S7: 20
A8: FN0615 | B8: POMAR BRUT ROSE 0,75LxC12 (N) | C8: CYM-FQ | D8: Espumantes | E8: Pomar | F8: 0,750 KG | G8: 1 | H8: 16% | I8: 0.27 | J8: 13.97 | K8: 16.48 | L8: 13.97 | M8: 16.48 | N8: 15.86 | O8: 18.4 | P8: 15.86 | Q8: 18.4 | R8: 19.53 | S8: 23
A9: FN0617 | B9: POMAR BRUT ROSE 0,75LxC6 (N) | C9: CYM-FQ | D9: Espumantes | E9: Pomar | F9: 0,750 KG | G9: 1 | H9: 16% | I9: 0.27 | J9: 13.97 | K9: 16.48 | L9: 13.97 | M9: 16.48 | N9: 15.86 | O9: 18.4 | P9: 15.86 | Q9: 18.4 | R9: 19.53 | S9: 23
A10: FN0625 | B10: POMAR BRUT E/E 0,75LxC6 (N) | C10: CYM-FQ | D10: Espumantes | E10: Pomar | F10: 0,000 KG | G10: 1 | H10: 16% | I10: 0.27 | J10: 43.14 | K10: 50.31 | L10: 43.14 | M10: 50.31 | N10: 48.27 | O10: 55.99 | P10: 48.27 | Q10: 55.99 | R10: 60.04 | S10: 69.99
A11: F04005 | B11: POLAR LIGHT RET 222MLx36UN | C11: CYM-FQ | D11: Light | E11: Polar Light | F11: 8,232 KG | G11: 36 | H11: 16% | I11: 2.24 | J11: 0.41 | K11: 0.54 | L11: 14.93 | M11: 19.56 | N11: 0.55 | O11: 0.64 | P11: 19.82 | Q11: 22.99 | R11: 22.53 | S11: 28.74
A12: F04014 | B12: POLAR LIGHT LAT 250MLx24UN | C12: CYM-FQ | D12: Light | E12: Polar Light | F12: 6,180 KG | G12: 24 | H12: 16% | I12: 2.16 | J12: 0.64 | K12: 0.83 | L12: 15.37 | M12: 19.99 | N12: 0.8 | O12: 0.92 | P12: 19.12 | Q12: 22.18 | R12: 21.73 | S12: 27.72
A13: F04017 | B13: POLAR LIGHT BAR 30Lx1PZ | C13: CYM-FQ | D13: Light | E13: Polar Light | F13: 0,000 KG | G13: 1 | H13: 16% | I13: 6.74 | J13: 58.44 | K13: 74.53 | L13: 58.44 | M13: 74.53 | N13: 74.35 | O13: 86.25 | P13: 74.35 | Q13: 86.25 | R13: 67.6 | S13: 86.25
... A57: FR0149 | B57: SANGRIA LA QUE MANDA ROSADA 1,75LX6UN | C57: CYM-FQ | D57: Sangría | E57: La Que Manda | F57: 10,659 KG | G57: 6 | H57: 16% | I57: 4.99 | J57: 2.82 | K57: 4.11 | L57: 16.94 | M57: 24.64 | N57: 4.11 | O57: 4.77 | P57: 24.68 | Q57: 28.63 | R57: 24.47 | S57: 34.5
A58: FR0159 | B58: SANGRIA CAROREÑA VERANO MOJITO LAT355x24 | C58: CYM-FQ | D58: Sangría | E58: Caroreña | G58: 24
A59: FR0160 | B59: SANGRIA LA QUE MANDA TINTA LAT250MLx24UN | C59: CYM-FQ | D59: Sangría | E59: La Que Manda | G59: 24
A60: F07103 | B60: MALTIN POLAR COCO LAT 250MLx24UN | C60: CYM-FQ | D60: Malta | E60: Maltin Polar | G60: 24
A61: F06066 | B61: KIT POLAR FEST NR 3,728L 2023 | C61: CYM-FQ | D61: Temporada | E61: Temporada | F61: 3,728 KG | G61: 12 | H61: 16% | I61: 1.17 | J61: 0.69 | K61: 0.9 | L61: 8.31 | M61: 10.81 | N61: 0.86 | O61: 1 | P61: 10.34 | Q61: 11.99 | R61: 11.75 | S61: 15
A62: F01001 | B62: POLAR PILSEN RET 222MLx36UN | C62: CYM-FQ | D62: Tradicional | E62: Polar Pilsen | F62: 8,032 KG | G62: 36 | H62: 16% | I62: 2.24 | J62: 0.41 | K62: 0.54 | L62: 14.93 | M62: 19.56 | N62: 0.55 | O62: 0.64 | P62: 19.82 | Q62: 22.99 | R62: 22.53 | S62: 28.74
A63: F01002 | B63: POLAR PILSEN RET 330MLx24UN | C63: CYM-FQ | D63: Tradicional | E63: Polar Pilsen | F63: 7,960 KG | G63: 24 | H63: 16% | I63: 2 | J63: 0.56 | K63: 0.73 | L63: 13.34 | M63: 17.47 | N63: 0.74 | O63: 0.86 | P63: 17.7 | Q63: 20.53 | R63: 20.12 | S63: 25.67
A64: F01003 | B64: POLAR PILSEN LAT 250MLx24UN | C64: CYM-FQ | D64: Tradicional | E64: Polar Pilsen | F64: 6,030 KG | G64: 24 | H64: 16% | I64: 2.16 | J64: 0.64 | K64: 0.83 | L64: 15.37 | M64: 19.99 | N64: 0.8 | O64: 0.92 | P64: 19.12 | Q64: 22.18 | R64: 21.73 | S64: 27.72
A65: F01004 | B65: POLAR PILSEN BAR 50Lx1PZ | C65: CYM-FQ | D65: Tradicional | E65: Polar Pilsen | F65: 0,000 KG | G65: 1 | H65: 16% | I65: 12.52 | J65: 108.54 | K65: 138.43 | L65: 108.54 | M65: 138.43 | N65: 138.08 | O65: 160.17 | P65: 138.08 | Q65: 160.17 | R65: 125.55 | S65: 160.17
A66: F01005 | B66: POLAR PILSEN BAR 30Lx1PZ | C66: CYM-FQ | D66: Tradicional | E66: Polar Pilsen | F66: 30,150 KG | G66: 1 | H66: 16% | I66: 6.74 | J66: 58.44 | K66: 74.53 | L66: 58.44 | M66: 74.53 | N66: 74.35 | O66: 86.25 | P66: 74.35 | Q66: 86.25 | R66: 67.6 | S66: 86.25
A67: F01063 | B67: POLAR PILSEN NR 355MLx12UN | C67: CYM-FQ | D67: Tradicional | E67: Polar Pilsen | F67: 4,281 KG | G67: 12 | H67: 16% | I67: 1.48 | J67: 0.88 | K67: 1.14 | L67: 10.53 | M67: 13.69 | N67: 1.09 | O67: 1.27 | P67: 13.1 | Q67: 15.2 | R67: 14.89 | S67: 19
A68: F01077 | B68: POLAR PILSEN LAT SLEEK 355MLx12UN | C68: CYM-FQ | D68: Tradicional | E68: Polar Pilsen | F68: 4,281 KG | G68: 12 | H68: 16% | I68: 1.3 | J68: 0.77 | K68: 1 | L68: 9.24 | M68: 12.02 | N68: 0.96 | O68: 1.11 | P68: 11.5 | Q68: 13.34 | R68: 13.07 | S68: 16.68
A69: F01081 | B69: POLAR FEST LAT SLEEK 355MLx12UN | C69: CYM-FQ | D69: Tradicional | E69: Polar Pilsen | F69: 4,281 KG | G69: 12 | H69: 16% | I69: 1.3 | J69: 0.77 | K69: 1 | L69: 9.24 | M69: 12.02 | N69: 0.96 | O69: 1.11 | P69: 11.5 | Q69: 13.34 | R69: 13.07 | S69: 16.68
A70: F01083 | B70: POLAR PILSEN LAT SLEEK 355MLx24UN | C70: CYM-FQ | D70: Tradicional | E70: Polar Pilsen | F70: 8,563 KG | G70: 24 | H70: 16% | I70: 2.61 | J70: 0.77 | K70: 1 | L70: 18.51 | M70: 24.08 | N70: 0.96 | O70: 1.11 | P70: 23.02 | Q70: 26.7 | R70: 26.16 | S70: 33.37
A71: FN0301 | B71: POMAR FRIZZANTE 0,75LxC12 (N) | C71: CYM-FQ | D71: Vino Nacional | E71: Pomar | F71: 0,750 KG | G71: 1 | H71: 16% | I71: 0.27 | J71: 5.92 | K71: 7.14 | L71: 5.92 | M71: 7.14 | N71: 6.9 | O71: 8 | P71: 6.9 | Q71: 8 | R71: 8.33 | S71: 10
A72: FN0304 | B72: POMAR FRIZZANTE ROSADO 0,75LxC12 (N) | C72: CYM-FQ | D72: Vino Nacional | E72: Pomar | F72: 0,750 KG | G72: 1 | H72: 16% | I72: 0.27 | J72: 5.92 | K72: 7.14 | L72: 5.92 | M72: 7.14 | N72: 6.9 | O72: 8 | P72: 6.9 | Q72: 8 | R72: 8.33 | S72: 10
... A77: FN0117 | B77: POMAR TINTO 0,75LxC12 (N) | C77: CYM-FQ | D77: Vino Nacional | E77: Terracota | F77: 0,750 KG | G77: 1 | H77: 16% | I77: 0.27 | J77: 4.67 | K77: 5.69 | L77: 4.67 | M77: 5.69 | N77: 5.52 | O77: 6.4 | P77: 5.52 | Q77: 6.4 | R77: 6.6 | S77: 8
A78: 1017662 | B78: MINALBA SPARKLING NARANJA PET500MLx12U | C78: PCV-FQ | D78: AGUA | E78: MINALBA | G78: 12 | H78: 16% | I78: 0.9 | J78: 1.05 | K78: 10.85 | L78: 12.59 | M78: 0.96 | N78: 1.12 | O78: 11.55 | P78: 13.4 | Q78: 1.15 | R78: 1.34
A79: 1017272 | B79: MINALBA SPARKLING LIMON PET 1Lx6UN | C79: PCV-FQ | D79: AGUA | E79: MINALBA | G79: 6 | H79: 16% | I79: 1.58 | J79: 1.83 | K79: 9.49 | L79: 11.01 | M79: 1.68 | N79: 1.95 | O79: 10.1 | P79: 11.72 | Q79: 2.02 | R79: 2.34
A80: 1017271 | B80: MINALBA SPARKLING PET 1Lx6UN | C80: PCV-FQ | D80: AGUA | E80: MINALBA | G80: 6 | H80: 16% | I80: 1.58 | J80: 1.83 | K80: 9.49 | L80: 11.01 | M80: 1.68 | N80: 1.95 | O80: 10.1 | P80: 11.72 | Q80: 2.02 | R80: 2.34
A81: 1017031 | B81: MINALBA SPARKLING TORONJA PET500MLx12U | C81: PCV-FQ | D81: AGUA | E81: MINALBA | G81: 12 | H81: 16% | I81: 0.9 | J81: 1.05 | K81: 10.85 | L81: 12.59 | M81: 0.96 | N81: 1.12 | O81: 11.55 | P81: 13.4 | Q81: 1.15 | R81: 1.34
A82: 1016692 | B82: MINALBA SPARKLING LIMON PET500MLx12UN | C82: PCV-FQ | D82: AGUA | E82: MINALBA | G82: 12 | H82: 16% | I82: 0.9 | J82: 1.05 | K82: 10.85 | L82: 12.59 | M82: 0.96 | N82: 1.12 | O82: 11.55 | P82: 13.4 | Q82: 1.15 | R82: 1.34
A83: 1016691 | B83: MINALBA SPARKLING PET 500MLx12UN | C83: PCV-FQ | D83: AGUA | E83: MINALBA | G83: 12 | H83: 16% | I83: 0.9 | J83: 1.05 | K83: 10.85 | L83: 12.59 | M83: 0.96 | N83: 1.12 | O83: 11.55 | P83: 13.4 | Q83: 1.15 | R83: 1.34
A84: 1013371 | B84: MINALBA AGUA PET 355MLx24UN | C84: PCV-FQ | D84: AGUA | E84: MINALBA | G84: 24 | H84: 16% | I84: 0.54 | J84: 0.62 | K84: 12.86 | L84: 14.92 | M84: 0.57 | N84: 0.66 | O84: 13.68 | P84: 15.87 | Q84: 0.68 | R84: 0.79
A85: 123517 | B85: MINALBA AGUA PET TR 600MLx24UN | C85: PCV-FQ | D85: AGUA | E85: MINALBA | G85: 24 | H85: 16% | I85: 0.68 | J85: 0.79 | K85: 16.32 | L85: 18.93 | M85: 0.72 | N85: 0.84 | O85: 17.36 | P85: 20.14 | Q85: 0.86 | R85: 1
A86: 95723 | B86: MINALBA AGUA PET S/G 5Lx2UN | C86: PCV-FQ | D86: AGUA | E86: MINALBA | G86: 2 | H86: 16% | I86: 3.72 | J86: 4.32 | K86: 7.44 | L86: 8.63 | M86: 3.96 | N86: 4.59 | O86: 7.92 | P86: 9.19 | Q86: 4.71 | R86: 5.46
A87: 95722 | B87: MINALBA AGUA PET S/G 1,5Lx12UN | C87: PCV-FQ | D87: AGUA | E87: MINALBA | G87: 12 | H87: 16% | I87: 1.26 | J87: 1.46 | K87: 15.15 | L87: 17.57 | M87: 1.34 | N87: 1.56 | O87: 16.12 | P87: 18.7 | Q87: 1.59 | R87: 1.84
A88: 1018185 | B88: GATORADE MANZANA PET 500MLx12UN | C88: PCV-FQ | D88: BEBIDAS DEPORTIVAS | E88: GATORADE | G88: 12 | H88: 16% | I88: 1.43 | J88: 1.66 | K88: 17.21 | L88: 19.96 | M88: 1.53 | N88: 1.77 | O88: 18.31 | P88: 21.24 | Q88: 1.88 | R88: 2.18
A89: 1015384 | B89: GATORADE MORA PET 500MLx12UN | C89: PCV-FQ | D89: BEBIDAS DEPORTIVAS | E89: GATORADE | G89: 12 | H89: 16% | I89: 1.43 | J89: 1.66 | K89: 17.21 | L89: 19.96 | M89: 1.53 | N89: 1.77 | O89: 18.31 | P89: 21.24 | Q89: 1.88 | R89: 2.18
... A177: 1012201 | B177: LIPTON LIMON PET 500MLx12UN | C177: PCV-FQ | D177: TE | E177: LIPTON ICE TE | G177: 12 | H177: 16% | I177: 1.34 | J177: 1.55 | K177: 16.03 | L177: 18.59 | M177: 1.42 | N177: 1.65 | O177: 17.05 | P177: 19.78 | Q177: 1.75 | R177: 2.03
A178: H201 | B178: MAZEITE ACEITE PET 1Lx12UN | C178: APC-FQ | D178: ACEITES | E178: MAZEITE | F178: 0,917 KG | G178: 12 | H178: 0,00% | I178: 4.42 | J178: 4.42 | K178: 53.04 | L178: 53.04 | M178: 4.8 | N178: 4.8 | O178: 57.6 | P178: 57.6 | Q178: 5.65 | R178: 5.65
A179: M007 | B179: SUPER CAN CACHORRO 2KGx6UN | C179: APC-FQ | D179: ALIMENTOS PARA PERROS | E179: SUPER CAN | F179: 2,000 KG | G179: 6 | H179: 16% | I179: 5.63 | J179: 6.53 | K179: 33.78 | L179: 39.18 | M179: 6.12 | N179: 7.1 | O179: 36.72 | P179: 42.6 | Q179: 7.75 | R179: 8.99
A180: M028 | B180: SUPER CAN CACHORRO 18KGx1UN | C180: APC-FQ | D180: ALIMENTOS PARA PERROS | E180: SUPER CAN | F180: 18,000 KG | G180: 1 | H180: 16% | I180: 34.39 | J180: 39.89 | K180: 34.39 | L180: 39.89 | M180: 37.38 | N180: 43.36 | O180: 37.38 | P180: 43.36 | Q180: 47.32 | R180: 54.89
A181: M033 | B181: SUPER CAN CARNE HUESO 18KILOS | C181: APC-FQ | D181: ALIMENTOS PARA PERROS | E181: SUPER CAN | F181: 18,000 KG | G181: 1 | H181: 16% | I181: 30.41 | J181: 35.28 | K181: 30.41 | L181: 35.28 | M181: 33.05 | N181: 38.34 | O181: 33.05 | P181: 38.34 | Q181: 41.84 | R181: 48.53
A182: M034 | B182: SUPER CAN POLLO 18KILOS | C182: APC-FQ | D182: ALIMENTOS PARA PERROS | E182: SUPER CAN | F182: 18,000 KG | G182: 1 | H182: 16% | I182: 30.41 | J182: 35.28 | K182: 30.41 | L182: 35.28 | M182: 33.05 | N182: 38.34 | O182: 33.05 | P182: 38.34 | Q182: 41.84 | R182: 48.53
A183: M340 | B183: SUPER CAN CARNE HUESO 4KGx5UN | C183: APC-FQ | D183: ALIMENTOS PARA PERROS | E183: SUPER CAN | F183: 4,000 KG | G183: 5 | H183: 16% | I183: 8.89 | J183: 10.31 | K183: 44.45 | L183: 51.56 | M183: 9.66 | N183: 11.21 | O183: 48.3 | P183: 56.03 | Q183: 12.23 | R183: 14.19
A184: M380 | B184: SUPER CAN CACHORROS 4KGx5UN | C184: APC-FQ | D184: ALIMENTOS PARA PERROS | E184: SUPER CAN | F184: 4,000 KG | G184: 5 | H184: 16% | I184: 9.93 | J184: 11.52 | K184: 49.65 | L184: 57.59 | M184: 10.79 | N184: 12.52 | O184: 53.95 | P184: 62.58 | Q184: 13.66 | R184: 15.85
A185: M800 | B185: SUPER CAN CARNE HUESO 2KGx6UN | C185: APC-FQ | D185: ALIMENTOS PARA PERROS | E185: SUPER CAN | F185: 2,000 KG | G185: 6 | H185: 16% | I185: 4.52 | J185: 5.24 | K185: 27.12 | L185: 31.46 | M185: 4.91 | N185: 5.7 | O185: 29.46 | P185: 34.17 | Q185: 6.21 | R185: 7.2
A186: M802 | B186: SUPER CAN CARNE HUESO 10KGx1UN | C186: APC-FQ | D186: ALIMENTOS PARA PERROS | E186: SUPER CAN | F186: 10,000 KG | G186: 1 | H186: 16% | I186: 20.12 | J186: 23.34 | K186: 20.12 | L186: 23.34 | M186: 21.88 | N186: 25.38 | O186: 21.88 | P186: 25.38 | Q186: 27.69 | R186: 32.12
A187: M029 | B187: CHAMPS PERRO CARNE TACO 20KGx1UN | C187: APC-FQ | D187: ALIMENTOS PARA PERROS | E187: CHAMPS | F187: 20,000 KG | G187: 1 | H187: 16% | I187: 25.03 | J187: 29.03 | K187: 25.03 | L187: 29.03 | M187: 27.21 | N187: 31.56 | O187: 27.21 | P187: 31.56 | Q187: 34.44 | R187: 39.95
A188: M324 | B188: DOGOURMET CARNE A LA PARRILLA 18KGx1UN | C188: APC-FQ | D188: ALIMENTOS PARA PERROS | E188: DOGOURMET | F188: 18,000 KG | G188: 1 | H188: 16% | I188: 42.44 | J188: 49.23 | K188: 42.44 | L188: 49.23 | M188: 46.13 | N188: 53.51 | O188: 46.13 | P188: 53.51 | Q188: 58.39 | R188: 67.73
A189: M326 | B189: DOGOURMET CARNE A LA PARRILLA 2KGx6UN | C189: APC-FQ | D189: ALIMENTOS PARA PERROS | E189: DOGOURMET | F189: 2,000 KG | G189: 6 | H189: 16% | I189: 6.22 | J189: 7.22 | K189: 37.32 | L189: 43.29 | M189: 6.76 | N189: 7.84 | O189: 40.56 | P189: 47.05 | Q189: 8.56 | R189: 9.93
... A265: L418 | B265: LAS LLAVES DET L.ACTIVA FLORAL 900Gx10UN | C265: APC-FQ | D265: DETERGENTES | E265: LAS LLAVES POLVO | F265: 0,900 KG | G265: 10 | H265: 16% | I265: 1.85 | J265: 2.15 | K265: 18.5 | L265: 21.46 | M265: 2.01 | N265: 2.33 | O265: 20.1 | P265: 23.32 | Q265: 2.54 | R265: 2.95
A266: L419 | B266: LAS LLAVES DET L.ACTIVA FLORAL 5KGx4UN | C266: APC-FQ | D266: DETERGENTES | E266: LAS LLAVES POLVO | F266: 5,000 KG | G266: 4 | H266: 16%
A267: L420 | B267: LAS LLAVES DET L.ACTIVA CITRICO 5KGx4UN | C267: APC-FQ | D267: DETERGENTES | E267: LAS LLAVES POLVO | F267: 5,000 KG | G267: 4 | H267: 16%
A268: L382 | B268: MULTI CLEAN DETER FRAG CITRICA 900Gx20UN | C268: APC-FQ | D268: DETERGENTES | E268: MULTI CLEAN | F268: 0,900 KG | G268: 20 | H268: 16% | I268: 1.85 | J268: 2.15 | K268: 37 | L268: 42.92 | M268: 2.01 | N268: 2.33 | O268: 40.2 | P268: 46.63 | Q268: 2.54 | R268: 2.95
A269: L383 | B269: MULTI CLEAN DETER FRAG CITRICA 400Gx30UN | C269: APC-FQ | D269: DETERGENTES | E269: MULTI CLEAN | F269: 0,400 KG | G269: 30 | H269: 16% | I269: 0.86 | J269: 1 | K269: 25.8 | L269: 29.93 | M269: 0.94 | N269: 1.09 | O269: 28.2 | P269: 32.71 | Q269: 1.19 | R269: 1.38
A270: L384 | B270: MULTI CLEAN DETER FRAG CITRICA 5KGx4UN | C270: APC-FQ | D270: DETERGENTES | E270: MULTI CLEAN | F270: 5,000 KG | G270: 4 | H270: 16% | I270: 10.29 | J270: 11.94 | K270: 41.16 | L270: 47.75 | M270: 11.18 | N270: 12.97 | O270: 44.72 | P270: 51.88 | Q270: 14.15 | R270: 16.41
A271: L390 | B271: MULTI CLEAN DETER FRAG FLORAL 900Gx20UN | C271: APC-FQ | D271: DETERGENTES | E271: MULTI CLEAN | F271: 0,900 KG | G271: 20 | H271: 16% | I271: 1.85 | J271: 2.15 | K271: 37 | L271: 42.92 | M271: 2.01 | N271: 2.33 | O271: 40.2 | P271: 46.63 | Q271: 2.54 | R271: 2.95
A272: L391 | B272: MULTI CLEAN DETER FRAG FLORAL 400Gx30UN | C272: APC-FQ | D272: DETERGENTES | E272: MULTI CLEAN | F272: 0,400 KG | G272: 30 | H272: 16% | I272: 0.86 | J272: 1 | K272: 25.8 | L272: 29.93 | M272: 0.94 | N272: 1.09 | O272: 28.2 | P272: 32.71 | Q272: 1.19 | R272: 1.38
A273: L392 | B273: MULTI CLEAN DETER FRAG FLORAL 5KGx4UN | C273: APC-FQ | D273: DETERGENTES | E273: MULTI CLEAN | F273: 5,000 KG | G273: 4 | H273: 16% | I273: 10.29 | J273: 11.94 | K273: 41.16 | L273: 47.75 | M273: 11.18 | N273: 12.97 | O273: 44.72 | P273: 51.88 | Q273: 14.15 | R273: 16.41
A274: L408 | B274: MULTI CLEAN DETER FRAG CITRICA 400Gx16UN | C274: APC-FQ | D274: DETERGENTES | E274: MULTI CLEAN | F274: 0,400 KG | G274: 16 | H274: 16% | I274: 0.86 | J274: 1 | K274: 13.76 | L274: 15.96 | M274: 0.94 | N274: 1.09 | O274: 15.04 | P274: 17.45 | Q274: 1.19 | R274: 1.38
A275: L409 | B275: MULTI CLEAN DETER FRAG FLORAL 400Gx16UN | C275: APC-FQ | D275: DETERGENTES | E275: MULTI CLEAN | F275: 0,400 KG | G275: 16 | H275: 16% | I275: 0.86 | J275: 1 | K275: 13.76 | L275: 15.96 | M275: 0.94 | N275: 1.09 | O275: 15.04 | P275: 17.45 | Q275: 1.19 | R275: 1.38
A276: L415 | B276: MULTI CLEAN DETER FRAG CITRICA 900Gx10UN | C276: APC-FQ | D276: DETERGENTES | E276: MULTI CLEAN | F276: 0,900 KG | G276: 10 | H276: 16% | I276: 1.85 | J276: 2.15 | K276: 18.5 | L276: 21.46 | M276: 2.01 | N276: 2.33 | O276: 20.1 | P276: 23.32 | Q276: 2.54 | R276: 2.95
A277: L416 | B277: MULTI CLEAN DETER FRAG FLORAL 900Gx10UN | C277: APC-FQ | D277: DETERGENTES | E277: MULTI CLEAN | F277: 0,900 KG | G277: 10 | H277: 16% | I277: 1.85 | J277: 2.15 | K277: 18.5 | L277: 21.46 | M277: 2.01 | N277: 2.33 | O277: 20.1 | P277: 23.32 | Q277: 2.54 | R277: 2.95
A278: Q138 | B278: TODDY CHIPS GALLETAS 24GX4UNIDX40 | C278: APC-FQ | D278: GALLETAS | E278: TODDY | F278: 0,024 KG | G278: 160 | H278: 16% | I278: 0.34 | J278: 0.39 | K278: 54.4 | L278: 63.1 | M278: 0.37 | N278: 0.43 | O278: 59.2 | P278: 68.67 | Q278: 0.47 | R278: 0.55
A279: M407 | B279: OHMAIGAT CASEROS Y DELICADOS 1,5KGX6UND | C279: APC-FQ | D279: GATOS | E279: OHMAIGAT | F279: 1,500 KG | G279: 6 | H279: 16% | I279: 9.37 | J279: 10.87 | K279: 56.22 | L279: 65.22 | M279: 10.19 | N279: 11.82 | O279: 61.14 | P279: 70.92 | Q279: 13.58 | R279: 15.75
... A414: Y074 | B414: YOGURT PIE DE LIMÓN MIGURT 125GX24UND | C414: APC-FQ | D414: Yogurt | E414: MIGURT | F414: 0,125 KG | G414: 24 | H414: 16% | I414: 1.03 | J414: 1.19 | K414: 24.72 | L414: 28.68 | M414: 1.12 | N414: 1.3 | O414: 26.88 | P414: 31.18 | Q414: 1.42 | R414: 1.65
A415: 80315781 | B415: GILLETTE BLIST PB3X4 SENSECARE 48GX36UN | C415: P&G-FQ | D415: AFEITADO | E415: Gillette UG | F415: 0,048 KG | G415: 36 | H415: 16% | I415: 5.54 | J415: 6.43 | K415: 199.44 | L415: 231.35 | M415: 6.16 | N415: 7.15 | O415: 221.76 | P415: 257.24 | Q415: 8 | R415: 9.28
A416: 80341300 | B416: GILLETTE MACH3 SISTEMA 37GX30UN | C416: P&G-FQ | D416: AFEITADO | E416: Gillette UG | F416: 0,037 KG | G416: 30 | H416: 16% | I416: 5.05 | J416: 5.86 | K416: 151.5 | L416: 175.74 | M416: 5.61 | N416: 6.51 | O416: 168.3 | P416: 195.23 | Q416: 7.28 | R416: 8.44
A417: 80341312 | B417: GILLETTE MACH3 CARTUCHOX2 16GX72UND | C417: P&G-FQ | D417: AFEITADO | E417: Gillette UG | F417: 0,016 KG | G417: 72 | H417: 16% | I417: 5.05 | J417: 5.86 | K417: 363.6 | L417: 421.78 | M417: 5.61 | N417: 6.51 | O417: 403.92 | P417: 468.55 | Q417: 7.28 | R417: 8.44
A418: 80341314 | B418: GILLETTE MACH3 CARTUCHOX4 20GX72UN | C418: P&G-FQ | D418: AFEITADO | E418: Gillette UG | F418: 0,020 KG | G418: 72 | H418: 16% | I418: 9.24 | J418: 10.72 | K418: 665.28 | L418: 771.72 | M418: 10.27 | N418: 11.91 | O418: 739.44 | P418: 857.75 | Q418: 13.34 | R418: 15.47
A419: 80354049 | B419: GILLETTE RIS PB2X24 PB3X4 MAS 236GX24RIS | C419: P&G-FQ | D419: AFEITADO | E419: Gillette UG | F419: 0,236 KG | G419: 24 | H419: 16% | I419: 21.13 | J419: 24.51 | K419: 507.12 | L419: 588.26 | M419: 23.49 | N419: 27.25 | O419: 563.76 | P419: 653.96 | Q419: 30.5 | R419: 35.38
A420: 80678858 | B420: GILLETTE BOLSA PB2X5UN MASC 39GX24UN | C420: P&G-FQ | D420: AFEITADO | E420: Gillette UG | F420: 0,039 KG | G420: 24 | H420: 16% | I420: 3.77 | J420: 4.37 | K420: 90.48 | L420: 104.96 | M420: 4.19 | N420: 4.86 | O420: 100.56 | P420: 116.65 | Q420: 5.44 | R420: 6.31
A421: 80678860 | B421: GILLETTE RISTRA PB2X24UN MASC 168GX24RIS | C421: P&G-FQ | D421: AFEITADO | E421: Gillette UG | F421: 0,168 KG | G421: 24 | H421: 16% | I421: 18.12 | J421: 21.02 | K421: 434.88 | L421: 504.46 | M421: 20.14 | N421: 23.36 | O421: 483.36 | P421: 560.7 | Q421: 26.15 | R421: 30.33
A422: 80682872 | B422: GILLETTE RIST HOJILL SUPERTHIN 60GX24RIS | C422: P&G-FQ | D422: AFEITADO | E422: Gillette UG | F422: 0,060 KG | G422: 24 | H422: 16% | I422: 18.12 | J422: 21.02 | K422: 434.88 | L422: 504.46 | M422: 20.13 | N422: 23.35 | O422: 483.12 | P422: 560.42 | Q422: 26.14 | R422: 30.32
A423: 80685855 | B423: GILLETTE RISTRA PB3X10UN MASC 120GX12RIS | C423: P&G-FQ | D423: AFEITADO | E423: Gillette UG | F423: 0,120 KG | G423: 12 | H423: 16% | I423: 12.08 | J423: 14.01 | K423: 144.96 | L423: 168.15 | M423: 13.42 | N423: 15.57 | O423: 161.04 | P423: 186.81 | Q423: 17.43 | R423: 20.22
A424: 80685905 | B424: GILLETTE BLISTER PB3X4UN MASC 46GX36UN | C424: P&G-FQ | D424: AFEITADO | E424: Gillette UG | F424: 0,046 KG | G424: 36 | H424: 16% | I424: 4.81 | J424: 5.58 | K424: 173.16 | L424: 200.87 | M424: 5.35 | N424: 6.21 | O424: 192.6 | P424: 223.42 | Q424: 6.95 | R424: 8.06
A425: 80685924 | B425: GILLETTE BLISTER PB3X2UN MASC 23GX72UN | C425: P&G-FQ | D425: AFEITADO | E425: Gillette UG | F425: 0,023 KG | G425: 72 | H425: 16% | I425: 2.69 | J425: 3.12 | K425: 193.68 | L425: 224.67 | M425: 2.99 | N425: 3.47 | O425: 215.28 | P425: 249.72 | Q425: 3.88 | R425: 4.5
A426: 80685930 | B426: GILLETTE BLIST PB3X2 SENSECARE 23GX72UN | C426: P&G-FQ | D426: AFEITADO | E426: Gillette UG | F426: 0,023 KG | G426: 72 | H426: 16% | I426: 3.07 | J426: 3.56 | K426: 221.04 | L426: 256.41 | M426: 3.41 | N426: 3.96 | O426: 245.52 | P426: 284.8 | Q426: 4.43 | R426: 5.14
... A638: 80692536 | B638: SECRET BARRA POWDPROT COTTON 45GX12UN | C638: P&G-FQ | D638: CUIDADOPERSONAL | E638: Secret | F638: 0,045 KG | G638: 12 | H638: 16% | I638: 3.87 | J638: 4.49 | K638: 46.44 | L638: 53.87 | M638: 4.3 | N638: 4.99 | O638: 51.6 | P638: 59.86 | Q638: 5.59 | R638: 6.48
A639: C200 | B639: ANZOATEGUI CAFE PREMIUM 100Gx30UN | C639: APC-FQ | D639: CAFE | E639: CAFE ANZOATEGUI | F639: 0,100 KG | G639: 30
A640: C201 | B640: ANZOATEGUI CAFE PREMIUM 200Gx20UN | C640: APC-FQ | D640: CAFE | E640: CAFE ANZOATEGUI | F640: 0,200 KG | G640: 20
A641: C202 | B641: ANZOATEGUI CAFE PREMIUM 500Gx10UN | C641: APC-FQ | D641: CAFE | E641: CAFE ANZOATEGUI | F641: 0,500 KG | G641: 10
A642: C210 | B642: BUEN CAFE PREMIUM 100Gx30UN | C642: APC-FQ | D642: CAFE | E642: BUEN CAFE | F642: 0,100 KG | G642: 30
A643: C211 | B643: BUEN CAFE PREMIUM 200Gx20UN | C643: APC-FQ | D643: CAFE | E643: BUEN CAFE | F643: 0,200 KG | G643: 20
A644: C213 | B644: BUEN CAFE PREMIUM 500Gx10UN | C644: APC-FQ | D644: CAFE | E644: BUEN CAFE | F644: 0,500 KG | G644: 10
